Workbook
Name 车队规模: '1-基础参数'!$C$13
Name 车租账期: '1-基础参数'!$C$23
Name 充电服务费: '1-基础参数'!$C$27
Name 充电服务费返佣率: '1-基础参数'!$C$28
Name 单边公里数: '1-基础参数'!$C$7
Name 工作日: '1-基础参数'!$C$11
Name 购置车辆数量: '1-基础参数'!$C$16
Name 购置车辆占比: '1-基础参数'!$C$14
Name 年化利率: '1-基础参数'!$C$24
Name 平台信息服务费率: '1-基础参数'!$C$26
Name 平台增值信息服务费: '1-基础参数'!$C$31
Name 日利率: '1-基础参数'!$C$25
Name 日趟数: '1-基础参数'!$C$10
Name 双边公里数: '1-基础参数'!$C$8
Name 税率: "'1-基础参数'!$C$32"
Name 月趟数: '1-基础参数'!$C$12
Name 运费账期: '1-基础参数'!$C$22
Name 运价: '1-基础参数'!$C$6
Name 载重: '1-基础参数'!$C$9
Name 租赁车辆数量: '1-基础参数'!$C$17
Name 租赁车辆占比: '1-基础参数'!$C$15

Sheet 0-财务模型说明
B2: 黄骅港电车物流项目 · 财务模型使用说明
B3: 本模型用于测算黄骅港电动车物流项目各参与方的资金分配与收益，支持购置/租赁两种车辆运营模式的对比分析。所有数据均动态联动，修改基础参数后全表自动更新。
B5: 一、工作表目录与功能说明
B7: 表序 | C7: 工作表名称 | D7: 功能定位 | E7: 主要内容 | F7: 上游依赖
B8: Sheet 0 | C8: 0-财务模型说明 | D8: 模型导航 & 说明文档 | E8: 模型架构、参与方说明、关键公式逻辑、使用指引 | F8: —
B9: Sheet 1 | C9: 1-基础参数 | D9: 唯一参数输入入口 | E9: 运营参数（运价/里程/车辆规模）、财务参数（利率/账期/返佣率）、运营数据汇总 | F9: 用户输入
B10: Sheet 2 | C10: 2-单车成本测算 | D10: 单车成本基础数据 | E10: 单车能耗成本、维保成本、司机成本、管理成本、保险费等各项明细 | F10: Sheet 1
B11: Sheet 3 | C11: 3-收益测算 | D11: 运营收益概览 | E11: 项目整体收入、成本、利润率的高层测算 | F11: Sheet 1, Sheet 2
B12: Sheet 3.5 | C12: 3.5-资金清分 ⭐ | D12: 资金分配核心引擎 | E12: 6层资金清分逻辑，购置/租赁并排，18个校验行全部=0 | F12: Sheet 1, Sheet 2
B13: Sheet 4 | C13: 4-相关方收益分配 | D13: 各方利益对比汇总 | E13: 11个参与方的收入/支出/净收益，购置/租赁双模式 | F13: Sheet 3.5
B14: Sheet 5 | C14: 5-资金流向图 | D14: 资金流向可视化 | E14: 15条资金流向路径、各方净收益占比、三大BD渠道收益对比 | F14: Sheet 3.5, Sheet 4
B15: Sheet 6 | C15: 6-敏感性分析 | D15: 情景分析 & 压力测试 | E15: 关键参数变动对收益影响的敏感性测算 | F15: Sheet 1, Sheet 3
B18: 二、参与方角色说明（共11方）
B20: # | C20: 参与方 | D20: 角色类型 | E20: 收益来源 | F20: 购置/租赁差异
B21: 1 | C21: 货主企业 | D21: 付款方（无收益） | E21: 支付全部运费，无直接收益 | F21: 两模式相同
B22: 2 | C22: 合同物流企业 | D22: BD渠道 · 总包方 | E22: 运费账期利息 + 车租账期利息 | F22: 租赁模式多车租账期利息
B23: 3 | C23: 物流服务公司 | D23: BD渠道 · 运营主体 | E23: 可分账额×45%留存 | F23: 租赁模式净可分账额减少（多扣租赁费）
B24: 4 | C24: 承运物流企业 | D24: 实际承运方 | E24: 分包款 - 进场费（司机/管理已由物流服务公司支付） | F24: 两模式相同
B25: 5 | C25: 平台公司 | D25: 平台运营方 | E25: 车赁溢价(200元/台) + 信息服务费 + 增值公司返佣 | F25: 购置无车赁溢价
B26: 6 | C26: 持车服务公司 | D26: BD渠道 · 车辆资产方 | E26: 车赁收入 - 融资租赁成本 - 保险费 | F26: 购置模式收益=0（无车赁）
B27: 7 | C27: 持车平台 | D27: 融资方（准银行角色） | E27: 融资租赁利息（融资成本×15%/1.15） | F27: 仅租赁模式有收益
B28: 8 | C28: 充电服务商 | D28: 能源供应商（经营性） | E28: 服务费自留90%（0.3元/度×90%） | F28: 两模式相同
B29: 9 | C29: 维保服务商 | D29: 维保供应商（过路） | E29: 净收益=0（过路企业） | F29: 两模式相同
B30: 10 | C30: 保险服务商 | D30: 保险代理（过路） | E30: 净收益=0（过路企业） | F30: 购置有保险，租赁=0
B31: 11 | C31: 增值服务公司 | D31: BD渠道 · 服务返佣 | E31: 三类BD佣金×75%（充电+维保+保险） | F31: 租赁多保险佣金
B34: 三、资金清分逻辑（6层架构）
B36: 层级 | C36: 清分主体 | D36: 核心逻辑 | E36: 净收益计算 | F36: 单车月净收益
B37: 第0层 | C37: 货主支付运费（资金入口） | D37: 运费 = 运价(210) × 载重(32) × 月趟数(11.2) × 车辆数 | E37: → 全额流入合同物流企业 | F37: 75,264 元/月（单车）
B38: 第1层 | C38: 合同物流企业清分 | D38: 留存账期利息（运费+车租）后，支付信息费、车租，余额转包 | E38: 净收益 = 运费账期利息 + 车租账期利息 | F38: 购置402元 / 租赁482元
B39: 第2层 | C39: 物流服务公司清分 | D39: 先扣硬性成本（能源/维保/司机/管理），余额净可分账额按55%/45%分账 | E39: 净收益 = 净可分账额 × 45% | F39: 购置10,151元 / 租赁3,384元
B40: 第2b层 | C40: 平台公司清分（车赁链） | D40: 仅租赁模式：收车赁费，转付持车服务公司（扣200元/台溢价） | E40: 净收益 = 200元×车辆数 + 信息费 + 增值返佣 | F40: 购置692元 / 租赁899元
B41: 第3层 | C41: 承运物流企业清分 | D41: 收分包款，扣进场费（司机/管理已在第2层统一支付） | E41: 净收益 = 分包款 - 进场费 | F41: 购置12,407元 / 租赁4,136元
B42: 第3b层 | C42: 持车服务公司清分（车赁链） | D42: 仅租赁模式：收平台转付车赁，支付融资租赁+保险 | E42: 净收益 = 车赁收入 - 融资成本 - 保险 | F42: 购置0元 / 租赁705元
B43: 第4层 | C43: 渠道服务商清分（4a/4b/4c） | D43: 充电商赚服务费90%；维保/保险为过路企业（净收益=0）；各自按比例向增值公司支付BD佣金 | E43: 充电净收益 = 服务费×90% | F43: 充电7,498元（两模式同）
B44: 第5层 | C44: 增值服务公司清分 | D44: 汇聚三类BD佣金（充电833+维保437+保险0/331），25%返佣平台 | E44: 净收益 = 三类佣金合计 × 75% | F44: 购置952元 / 租赁1,201元
B47: 四、关键参数一览（1-基础参数表）
B49: 参数名称 | C49: 单元格 | D49: 当前值 | E49: 作用说明 | F49: 影响层级
B50: 运价 | C50: C6 | D50: 210 元/吨 | E50: 决定运费总收入基数 | F50: 第0层～全链
B51: 月趟数 | C51: C12 | D51: 11.2 趟/月 | E51: 运价×载重×月趟数×车辆数=总收入 | F51: 第0层
B52: 车辆数/计算模式 | C52: C37/C40 | D52: 1（单车模式） | E52: 切换1=单车 / 500=车队，全表跟随变化 | F52: 全表
B53: 承运方分账比例 | C53: C33 | D53: 0.55 | E53: 物流服务公司分账给承运方的比例（可调） | F53: 第2层、第3层
B54: 充电服务费 | C54: C27 | D54: 0.3 元/度 | E54: 电价0.97中的服务费部分，返佣基数 | F54: 第4a层
B55: 充电返佣率 | C55: C28 | D55: 0.1 | E55: 仅对充电服务费(0.3元)部分计算返佣 | F55: 第4a层、第5层
B56: 维保返佣率 | C56: C29 | D56: 0.1 | E56: 维保费全额×10%向增值公司支付 | F56: 第4b层、第5层
B57: 保险佣金率 | C57: C30 | D57: 0.15 | E57: 保险费×15%为渠道佣金（购置有，租赁=0） | F57: 第4c层、第5层
B58: 增值公司返佣平台 | C58: C34 | D58: 0.25 | E58: 增值服务公司将三类佣金合计的25%返给平台 | F58: 第5层、第2b层
B59: 运费账期 | C59: C22 | D59: 30 天 | E59: 影响合同物流企业账期利息收入 | F59: 第1层
B60: 车租账期 | C60: C23 | D60: 30 天 | E60: 租赁模式下影响合同物流企业车租账期利息 | F60: 第1层
B61: 年化利率 | C61: C24 | D61: 0.065 | E61: 计算账期利息的年化利率 | F61: 第1层
B62: 平台信息服务费率 | C62: C26 | D62: 5‰ | E62: 转包金额×5‰，合同物流企业支付给平台 | F62: 第1层、第2b层
B65: 五、核心公式逻辑说明
B67: 公式名称 | C67: 所在位置 | D67: 公式逻辑（D:E合并） | F67: 数值示例（单车购置）
B68: 运费总收入 | C68: 3.5 D9/E9 | D68: 运价(210) × 载重(32) × 月趟数(11.2) × 车辆数(1) | F68: 75,264 元/月
B69: 运费账期利息 | C69: 3.5 D12/E12 | D69: 运费总收入 × (年化利率6.5%÷365) × 账期30天 | F69: 402 元/月
B70: 平台信息服务费 | C70: 3.5 D14/E14 | D70: 转包款 × 平台服务费率(5‰) | F70: 374 元/月
B71: 净可分账额 | C71: 3.5 D27/E27 | D71: 转包款 - 能源费 - 维保费 - 司机成本 - 管理费（硬性成本先全扣） | F71: 22,558 元/月
B72: 承运方分包款 | C72: 3.5 D28/E28 | D72: 净可分账额 × 承运方分账比例(C33=55%) | F72: 12,407 元/月
B73: 充电佣金 重要 | C73: 3.5 D65/E65 | D73: 能源费 × (服务费0.3 ÷ 电价0.97) × 返佣率10% 注：仅对服务费部分，不含基础电费0.67 | F73: 833 元/月
B74: 充电服务商净收益 | C74: 3.5 D66/E66 | D74: 能源费 × (0.3÷0.97) × (1-10%) 充电商自留服务费90% | F74: 7,498 元/月
B75: 平台公司净收益 | C75: Sheet4 F30/I30 | D75: 购置=信息费+增值返佣 租赁=车赁溢价(200/台)+信息费+增值返佣 | F75: 购置691/租赁899元
B76: 融资租赁成本 | C76: 3.5 E53 | D76: 购置月均摊销 × 1.15 持车平台净收益=收入×15%÷1.15 | F76: 成本11,845/净利1,545元
B77: 增值公司返佣平台 | C77: 3.5 D89/E89 | D77: 三类BD佣金合计(充电+维保+保险) × 返佣率(C34=25%) | F77: 购置317/租赁400元
B80: 六、核心数据汇总（单车月度，基于当前参数）
B82: 指标 | C82: 购置模式 | D82: 租赁模式 | E82: 差异 | F82: 说明
B83: 运费总收入（元） | C83: 75264 | D83: 75264 | E83: 0 | F83: 两模式运费相同
B84: 合同物流企业净收益 | C84: 402 | D84: 482 | E84: 80 | F84: 租赁多车租账期利息
B85: 物流服务公司净收益 | C85: 9983 | D85: 3249 | E85: -6734 | F85: 租赁须承担车辆租赁费，可分账额减少
B86: 承运物流企业净收益 | C86: 12201 | D86: 3971 | E86: -8230 | F86: 随物流服务公司可分账额变动
B87: 平台公司净收益 | C87: 692 | D87: 899 | E87: 207 | F87: 租赁多200元/台车赁溢价
B88: 持车服务公司净收益 | C88: 0 | D88: 705 | E88: 705 | F88: 购置无此收益
B89: 持车平台净收益（融资利息） | C89: 0 | D89: 1545 | E89: 1545 | F89: 购置无此收益
B90: 充电服务商净收益 | C90: 7498 | D90: 7498 | E90: 0 | F90: 两模式能源费相同
B91: 维保服务商净收益 | C91: 0 | D91: 0 | E91: 0 | F91: 过路企业
B92: 保险服务商净收益 | C92: 0 | D92: 0 | E92: 0 | F92: 过路企业
B93: 增值服务公司净收益 | C93: 952 | D93: 1201 | E93: 249 | F93: 租赁多保险佣金来源
B94: 全参与方净收益合计 | C94: 31728 | D94: 19550 | E94: -12178 | F94: 购置模式综合收益更高
B95: 净收益/运费比率 | C95: 0.422 | D95: 0.26 | E95: -16.3ppt | F95: 购置模式经济性更优

Sheet 1-基础参数
B2: 黄骅港电车物流项目-基础参数设置表
B4: 一、运营基础参数
B5: 参数名称 | C5: 数值 | D5: 单位 | E5: 说明 | F5: 来源
B6: 运价 | C6: 210 | D6: 元/吨趟 | E6: 每吨货物运输价格 | F6: 市场价格
B7: 单边公里数 | C7: 650 | D7: 公里 | E7: 单程运输距离 | F7: 实际路程测算
B8: 双边公里数 | C8: 1300 | D8: 公里 | E8: 往返总距离
B9: 载重 | C9: 32 | D9: 吨 | E9: 单车额定载重 | F9: 车辆参数
B10: 日趟数 | C10: 0.4 | D10: 趟/日 | E10: 每车每日平均趟数 | F10: 运营规划
B11: 工作日 | C11: 28 | D11: 天/月 | E11: 每月实际工作天数 | F11: 运营规划
B12: 月趟数 | C12: =C10*C11 -> 11.2 | D12: 趟/月 | E12: 每月总趟数 | F12: 计算值
B13: 车队规模 | C13: 500 | D13: 辆 | E13: 总运营车辆数 | F13: 项目规划
B14: 购置车辆占比 | C14: 1 | E14: 购置车辆比例 | F14: 资金规划
B15: 租赁车辆占比 | C15: 1 | E15: 租赁车辆比例 | F15: 资金规划
B16: 购置车辆数量 | C16: =C13*C14 -> 500 | D16: 辆 | E16: 购置车辆总数 | F16: 计算值
B17: 租赁车辆数量 | C17: =C13*C15 -> 500 | D17: 辆 | E17: 租赁车辆总数 | F17: 计算值
B20: 二、财务与账期参数
B21: 参数名称 | C21: 数值 | D21: 单位 | E21: 说明 | F21: 来源
B22: 运费账期 | C22: 30 | D22: 天 | E22: 货主付款周期 | F22: 合同约定
B23: 车租账期 | C23: 30 | D23: 天 | E23: 租赁费支付周期 | F23: 租赁协议
B24: 年化利率 | C24: 0.055 | E24: 资金成本年化利率 | F24: 市场利率
B25: 日利率 | C25: =C24/365 -> 0.00015068493 | E25: 日资金成本 | F25: 计算值
B26: 平台物流信息服务费率 | C26: 0.005 | E26: 平台运输信息服务费率 | F26: 平台政策
B27: 充电服务费 | C27: 0.3 | D27: 元/度 | E27: 充电桩服务费 | F27: 充电站定价
B28: 充电服务费返佣率 | C28: 0.1 | E28: 充电服务渠道返佣比例 | F28: 平台政策
B29: 维保服务费返佣率 | C29: 0.1 | E29: 维保服务渠道返佣比例 | F29: 平台政策
B30: 保险服务费渠道佣金 | C30: 0.15 | E30: 保险服务渠道佣金 | F30: 平台政策
B31: 平台增值信息服务费 | C31: 0.25 | E31: 平台增值信息服务费率 | F31: 平台政策
B32: 税率 | C32: 0.09 | E32: 运输服务增值税税率 | F32: 税务规定
B33: 承运方分账比例 | C33: 0.55 | E33: 物流服务公司向承运方分配的比例 | F33: 合同约定
B34: 增値服务公司返佣率（向平台公司） | C34: 0.25 | D34: BD渠道收益中向平台公司返佣的比例
B35: 三、运营数据汇总（可切换单车/车队）
B37: 计算模式 | C37: 1 | D37: (1=单车, 500=车队规模) | E37: 说明：修改此处数值可切换单车或车队计算
B39: 参数名称 | C39: 数值 | D39: 单位 | E39: 说明
B40: 计算车辆数 | C40: =IF(C37=1,1,C13) -> 1 | D40: 辆 | E40: 根据模式自动切换
B41: 单车月里程 | C41: =C12*C8 -> 14560 | D41: 公里 | E41: 月趟数×双边公里
B42: 单车月运输吨数 | C42: =C12*C9 -> 358.4 | D42: 吨 | E42: 月趟数×载重
B43: 月度累计里程 | C43: =C41*C40 -> 14560 | D43: 公里 | E43: 单车月里程×车辆数
B44: 月度累计运输吨数 | C44: =C42*C40 -> 358.4 | D44: 吨 | E44: 单车运输吨数×车辆数
B45: 月度累计能源消耗(去程) | C45: =C43*C16*0.97/100 -> 70616 | D45: 千度 | E45: 累计里程×去程耗电÷2×电价÷100
B46: 月度累计能源消耗(回程) | C46: =C43*C17*0.97/100 -> 70616 | D46: 千度 | E46: 累计里程×回程耗电÷2×电价÷100
B47: 月度累计能源消耗(总) | C47: =(C45+C46) -> 141232 | D47: 千度 | E47: 去程+回程总能耗

Sheet 2-单车成本测算
B2: 单车全生命周期成本测算表
B4: 成本类别 | C4: 成本明细 | D4: 单位 | E4: 购置车辆成本 | F4: 租赁车辆成本 | G4: 购置单车月成本 | H4: 租赁单车月成本 | I4: 购置车队月成本 | J4: 租赁车队月成本 | K4: 说明
B5: 车辆购置 | C5: 车头价格 | D5: 元/辆 | E5: 390000 | F5: 0 | H5: 0 | J5: 0 | K5: 车头采购成本
C6: 挂车价格 | D6: 元/辆 | E6: 70000 | F6: 70000 | K6: 挂车采购/租赁
C7: 购车补贴 | D7: 元/辆 | E7: 0 | F7: 0 | H7: 0 | J7: 0 | K7: 政府购车补贴
C8: 金融利息(36期5.5%) | D8: 元 | E8: =PMT(0.055/12,36,-E5*0.9)*36-E5*0.9 -> 30555.415 | F8: 0 | H8: 0 | J8: 0 | K8: 贷款利息总额
C9: 购置成本月均摊销 | D9: 元/月 | G9: =(E5+E6+E7+E8)/48 -> 10219.904 | H9: =0 -> 0 | I9: =G9*购置车辆数量 -> 5109952.2 | J9: =H9*购置车辆数量 -> 0 | K9: 4年摊销
B10: 租赁费用 | C10: 车辆月租金 | D10: 元/辆/月 | E10: 0 | F10: 13500 | G10: 0 | H10: =F10+(F6)/48 -> 14958.333 | I10: 0 | J10: =H10*购置车辆数量 -> 7479166.7 | K10: 车头租金+振车摸销（48期）
B11: 保险费用 | C11: 交强险 | D11: 元/年 | E11: 4480 | F11: 0 | G11: =E11/12 -> 373.33333 | H11: 0 | I11: =G11*'1-基础参数'!C16 -> 186666.67 | J11: 0
C12: 商业险 | D12: 元/年 | E12: 20920 | F12: 0 | G12: =E12/12 -> 1743.3333 | H12: 0 | I12: =G12*'1-基础参数'!C16 -> 871666.67 | J12: 0
C13: 超赔险 | D13: 元/年 | E13: 1100 | F13: 0 | G13: =E13/12 -> 91.666667 | H13: 0 | I13: =G13*'1-基础参数'!C16 -> 45833.333 | J13: 0
C14: 保险小计 | D14: 元/月 | G14: =SUM(G11:G13) -> 2208.3333 | H14: 0 | I14: =G14*购置车辆数量 -> 1104166.7 | J14: =H16*'1-基础参数'!C17 -> 0
B15: 能源费用 | C15: 电价 | D15: 元/度 | E15: 0.97 | F15: 0.97
C16: 满载百公里耗电 | D16: 度/百公里 | E16: 185 | F16: 185
C17: 空载百公里耗电 | D17: 度/百公里 | E17: 150 | F17: 150
C18: 去程能耗成本 | D18: 元/趟 | E18: =E16/100*单边公里数 -> 1202.5 | F18: =F16/100*单边公里数 -> 1202.5 | G18: =E18 -> 1202.5 | H18: =F18 -> 1202.5 | I18: =G18*'1-基础参数'!$C$13*'1-基础参数'!$C$14 -> 601250 | J18: =H18*'1-基础参数'!$C$13*'1-基础参数'!$C$15 -> 601250 | K18: 下坡满载
C19: 回程能耗成本 | D19: 元/趟 | E19: =E16/100*单边公里数 -> 1202.5 | F19: =F16/100*单边公里数 -> 1202.5 | G19: =E19 -> 1202.5 | H19: =F19 -> 1202.5 | I19: =G19*'1-基础参数'!$C$13*'1-基础参数'!$C$14 -> 601250 | J19: =H19*'1-基础参数'!$C$13*'1-基础参数'!$C$15 -> 601250 | K19: 上坡空载
C20: 单趟能耗成本 | D20: 元/趟 | E20: =SUM(E18:E19) -> 2405 | F20: =SUM(F18:F19) -> 2405 | G20: =E20 -> 2405 | H20: =F20 -> 2405 | K20: 往返总成本
C21: 月能源费用 | D21: 元/月 | G21: =G20*'1-基础参数'!$C$12 -> 26936 | H21: =H20*'1-基础参数'!$C$12 -> 26936 | I21: =G21*购置车辆数量 -> 13468000 | J21: =H21*购置车辆数量 -> 13468000
B22: 司机费用 | C22: 司机工资 | D22: 元/人/月 | E22: 10000 | F22: 10000
C23: 人车比 | D23: 人/车 | E23: 2 | F23: 2 | K23: 双班制
C24: 单车司机成本 | D24: 元/月 | G24: =E22*E23 -> 20000 | H24: =F22*F23 -> 20000 | I24: =G24*购置车辆数量 -> 10000000 | J24: =H24*购置车辆数量 -> 10000000
B25: 维保费用 | C25: 保养周期 | D25: 公里/次 | E25: 10000 | F25: 10000
C26: 单次保养费用 | D26: 元/次 | E26: 3000 | F26: 3000
C27: 每公里维保成本 | D27: 元/公里 | E27: =E26/E25 -> 0.3 | F27: =F26/F25 -> 0.3
C28: 月维保费用 | D28: 元/月 | G28: =E27*'1-基础参数'!$C$8*'1-基础参数'!$C$12 -> 4368 | H28: =F27*'1-基础参数'!$C$8*'1-基础参数'!$C$12 -> 4368 | I28: =G28*购置车辆数量 -> 2184000 | J28: =H28*购置车辆数量 -> 2184000
B29: 管理费用 | C29: 管理人员工资 | D29: 元/人/月 | E29: 15000 | F29: 15000
C30: 管理人员配置 | D30: 人 | E30: 6 | F30: 6 | K30: 车管+调度
C31: 可管理车辆数 | D31: 辆 | E31: 90 | F31: 90
C32: 单车管理成本 | D32: 元/月 | E32: =E29*E30/E31 -> 1000 | F32: =F29*F30/F31 -> 1000 | G32: =IF(E30=0,0,E29*E30/E31) -> 1000 | H32: =IF(F30=0,0,F29*F30/F31) -> 1000 | I32: =G32*购置车辆数量 -> 500000 | J32: =H32*购置车辆数量 -> 500000
B33: 其他费用 | C33: 进场费 | D33: 元/吨 | E33: 0 | F33: 0 | G33: =E33*'1-基础参数'!C9*'1-基础参数'!C12 -> 0 | H33: =F33*'1-基础参数'!C9*'1-基础参数'!C12 -> 0 | I33: =G33*'1-基础参数'!C16 -> 0 | J33: =H33*'1-基础参数'!C18 -> 0
B34: 税费 | C34: 增值税及附加(收入×9%) | D34: 元/月 | E34: =ROUND('1-基础参数'!C6*'1-基础参数'!C9*'1-基础参数'!C12*'1-基础参数'!$C$32,2) -> 6773.76 | F34: =ROUND('1-基础参数'!C6*'1-基础参数'!C9*'1-基础参数'!C12*'1-基础参数'!$C$32,2) -> 6773.76 | G34: =ROUND('1-基础参数'!C6*'1-基础参数'!C9*'1-基础参数'!C12*'1-基础参数'!$C$32,2) -> 6773.76 | H34: =ROUND('1-基础参数'!C6*'1-基础参数'!C9*'1-基础参数'!C12*'1-基础参数'!$C$32,2) -> 6773.76 | I34: =G34*购置车辆数量 -> 3386880 | J34: =H34*租赁车辆数量 -> 3386880 | K34: 含在合计内（价税分离）
C35: 月度成本合计 | D35: 元/月 | G35: =G32+G28+G24+G21+G14+G9+G34 -> 71505.998 | H35: =H32+H28+H24+H21+H14+H9+H10+H34 -> 74036.093 | I35: =G35*购置车辆数量 -> 35752999 | J35: =H35*租赁车辆数量 -> 37018047
B37: 详细边际成本分析
B38: 成本项 | C38: 购置-单吨公里 | D38: 租赁-单吨公里 | E38: 购置-单吨每趟 | F38: 租赁-单吨每趟 | G38: 购置-单车公里 | H38: 租赁-单车公里 | I38: 购置-单车每趟 | J38: 租赁-单车每趟 | K38: 单位
B39: 车辆购置成本 | C39: =G9/('1-基础参数'!C41*'1-基础参数'!C9) -> 0.021934891 | D39: =H9/('1-基础参数'!C41*'1-基础参数'!C9) -> 0 | E39: =G9/('1-基础参数'!C12*'1-基础参数'!C9) -> 28.515358 | F39: =H9/('1-基础参数'!C12*'1-基础参数'!C9) -> 0 | G39: =G9/'1-基础参数'!C41 -> 0.70191652 | H39: =H9/'1-基础参数'!C41 -> 0 | I39: =G9/'1-基础参数'!C12 -> 912.49147 | J39: =H9/'1-基础参数'!C12 -> 0 | K39: 元
B40: 租赁费用 | C40: =G10/('1-基础参数'!C41*'1-基础参数'!C9) -> 0 | D40: =H10/('1-基础参数'!C41*'1-基础参数'!C9) -> 0.032104939 | E40: =G10/('1-基础参数'!C12*'1-基础参数'!C9) -> 0 | F40: =H10/('1-基础参数'!C12*'1-基础参数'!C9) -> 41.736421 | G40: =G10/'1-基础参数'!C41 -> 0 | H40: =H10/'1-基础参数'!C41 -> 1.0273581 | I40: =G10/'1-基础参数'!C12 -> 0 | J40: =H10/'1-基础参数'!C12 -> 1335.5655 | K40: 元
B41: 保险费用 | C41: =G14/('1-基础参数'!C41*'1-基础参数'!C9) -> 0.0047397264 | D41: =H14/('1-基础参数'!C41*'1-基础参数'!C9) -> 0 | E41: =G14/('1-基础参数'!C12*'1-基础参数'!C9) -> 6.1616443 | F41: =H14/('1-基础参数'!C12*'1-基础参数'!C9) -> 0 | G41: =G14/'1-基础参数'!C41 -> 0.15167125 | H41: =H14/'1-基础参数'!C41 -> 0 | I41: =G14/'1-基础参数'!C12 -> 197.17262 | J41: =H14/'1-基础参数'!C12 -> 0 | K41: 元
B42: 能源费用 | C42: =G21/('1-基础参数'!C41*'1-基础参数'!C9) -> 0.0578125 | D42: =H21/('1-基础参数'!C41*'1-基础参数'!C9) -> 0.0578125 | E42: =G21/('1-基础参数'!C12*'1-基础参数'!C9) -> 75.15625 | F42: =H21/('1-基础参数'!C12*'1-基础参数'!C9) -> 75.15625 | G42: =G21/'1-基础参数'!C41 -> 1.85 | H42: =H21/'1-基础参数'!C41 -> 1.85 | I42: =G21/'1-基础参数'!C12 -> 2405 | J42: =H21/'1-基础参数'!C12 -> 2405 | K42: 元
B43: 司机费用 | C43: =G24/('1-基础参数'!C41*'1-基础参数'!C9) -> 0.042925824 | D43: =H24/('1-基础参数'!C41*'1-基础参数'!C9) -> 0.042925824 | E43: =G24/('1-基础参数'!C12*'1-基础参数'!C9) -> 55.803571 | F43: =H24/('1-基础参数'!C12*'1-基础参数'!C9) -> 55.803571 | G43: =G24/'1-基础参数'!C41 -> 1.3736264 | H43: =H24/'1-基础参数'!C41 -> 1.3736264 | I43: =G24/'1-基础参数'!C12 -> 1785.7143 | J43: =H24/'1-基础参数'!C12 -> 1785.7143 | K43: 元
B44: 维保费用 | C44: =G28/('1-基础参数'!C41*'1-基础参数'!C9) -> 0.009375 | D44: =H28/('1-基础参数'!C41*'1-基础参数'!C9) -> 0.009375 | E44: =G28/('1-基础参数'!C12*'1-基础参数'!C9) -> 12.1875 | F44: =H28/('1-基础参数'!C12*'1-基础参数'!C9) -> 12.1875 | G44: =G28/'1-基础参数'!C41 -> 0.3 | H44: =H28/'1-基础参数'!C41 -> 0.3 | I44: =G28/'1-基础参数'!C12 -> 390 | J44: =H28/'1-基础参数'!C12 -> 390 | K44: 元
B45: 管理费用 | C45: =G32/('1-基础参数'!C41*'1-基础参数'!C9) -> 0.0021462912 | D45: =H32/('1-基础参数'!C41*'1-基础参数'!C9) -> 0.0021462912 | E45: =G32/('1-基础参数'!C12*'1-基础参数'!C9) -> 2.7901786 | F45: =H32/('1-基础参数'!C12*'1-基础参数'!C9) -> 2.7901786 | G45: =G32/'1-基础参数'!C41 -> 0.068681319 | H45: =H32/'1-基础参数'!C41 -> 0.068681319 | I45: =G32/'1-基础参数'!C12 -> 89.285714 | J45: =H32/'1-基础参数'!C12 -> 89.285714 | K45: 元
B46: 其他费用 | C46: =G33/('1-基础参数'!C41*'1-基础参数'!C9) -> 0 | D46: =H33/('1-基础参数'!C41*'1-基础参数'!C9) -> 0 | E46: =G33/('1-基础参数'!C12*'1-基础参数'!C9) -> 0 | F46: =H33/('1-基础参数'!C12*'1-基础参数'!C9) -> 0 | G46: =G33/'1-基础参数'!C41 -> 0 | H46: =H33/'1-基础参数'!C41 -> 0 | I46: =G33/'1-基础参数'!C12 -> 0 | J46: =H33/'1-基础参数'!C12 -> 0 | K46: 元
B47: 税费 | C47: =G34/('1-基础参数'!C41*'1-基础参数'!C9) -> 0.014538462 | D47: =H34/('1-基础参数'!C41*'1-基础参数'!C9) -> 0.014538462 | E47: =G34/('1-基础参数'!C12*'1-基础参数'!C9) -> 18.9 | F47: =H34/('1-基础参数'!C12*'1-基础参数'!C9) -> 18.9 | G47: =G34/'1-基础参数'!C41 -> 0.46523077 | H47: =H34/'1-基础参数'!C41 -> 0.46523077 | I47: =G34/'1-基础参数'!C12 -> 604.8 | J47: =H34/'1-基础参数'!C12 -> 604.8 | K47: 元
B48: 总成本 | C48: =SUM(C39:C47) -> 0.15347269 | D48: =SUM(D39:D47) -> 0.15890302 | E48: =SUM(E39:E47) -> 199.5145 | F48: =SUM(F39:F47) -> 206.57392 | G48: =SUM(G39:G47) -> 4.9111262 | H48: =SUM(H39:H47) -> 5.0848965 | I48: =SUM(I39:I47) -> 6384.4641 | J48: =SUM(J39:J47) -> 6610.3655 | K48: 元

Sheet 3-收益测算
B2: 项目月度收益测算表
B4: 项目 | C4: 计算口径 | D4: 购置单车 | E4: 租赁单车 | F4: 购置车队 | G4: 租赁车队 | H4: 单位 | I4: 说明
B5: 一、营业收入
B6: 运输收入 | C6: 运价×载重×月趟数 | D6: ='1-基础参数'!C6*'1-基础参数'!C9*'1-基础参数'!C12 -> 75264 | E6: ='1-基础参数'!C6*'1-基础参数'!C9*'1-基础参数'!C12 -> 75264 | F6: =D6*'1-基础参数'!C16 -> 37632000 | G6: =E6*'1-基础参数'!C17 -> 37632000 | H6: 元/月 | I6: 运费总收入
B8: 二、营业成本
B9: 车辆购置成本 | C9: 引用成本表 | D9: ='2-单车成本测算'!G9 -> 10219.904 | E9: ='2-单车成本测算'!H9 -> 0 | F9: ='2-单车成本测算'!I9 -> 5109952.2 | G9: ='2-单车成本测算'!J9 -> 0 | H9: 元/月 | I9: 购置成本摊销
B10: 租赁费用 | C10: 引用成本表 | D10: ='2-单车成本测算'!G10 -> 0 | E10: ='2-单车成本测算'!H10 -> 14958.333 | F10: ='2-单车成本测算'!I10 -> 0 | G10: ='2-单车成本测算'!J10 -> 7479166.7 | H10: 元/月 | I10: 车辆租金
B11: 保险费用 | C11: 引用成本表 | D11: ='2-单车成本测算'!G14 -> 2208.3333 | E11: ='2-单车成本测算'!H14 -> 0 | F11: ='2-单车成本测算'!I14 -> 1104166.7 | G11: ='2-单车成本测算'!J14 -> 0 | H11: 元/月 | I11: 交强险+商业险+超赔险
B12: 能源费用 | C12: 引用成本表 | D12: ='2-单车成本测算'!G21 -> 26936 | E12: ='2-单车成本测算'!H21 -> 26936 | F12: ='2-单车成本测算'!I21 -> 13468000 | G12: ='2-单车成本测算'!J21 -> 13468000 | H12: 元/月 | I12: 充电费用
B13: 司机费用 | C13: 引用成本表 | D13: ='2-单车成本测算'!G24 -> 20000 | E13: ='2-单车成本测算'!H24 -> 20000 | F13: ='2-单车成本测算'!I24 -> 10000000 | G13: ='2-单车成本测算'!J24 -> 10000000 | H13: 元/月 | I13: 司机工资
B14: 维保费用 | C14: 引用成本表 | D14: ='2-单车成本测算'!G28 -> 4368 | E14: ='2-单车成本测算'!H28 -> 4368 | F14: ='2-单车成本测算'!I28 -> 2184000 | G14: ='2-单车成本测算'!J28 -> 2184000 | H14: 元/月 | I14: 维修保养
B15: 管理费用 | C15: 引用成本表 | D15: ='2-单车成本测算'!G32 -> 1000 | E15: ='2-单车成本测算'!H32 -> 1000 | F15: ='2-单车成本测算'!I32 -> 500000 | G15: ='2-单车成本测算'!J32 -> 500000 | H15: 元/月 | I15: 管理成本
B16: 其他费用 | C16: 引用成本表 | D16: ='2-单车成本测算'!G33 -> 0 | E16: ='2-单车成本测算'!H33 -> 0 | F16: ='2-单车成本测算'!I33 -> 0 | G16: ='2-单车成本测算'!J33 -> 0 | H16: 元/月 | I16: 进场费等
B17: 税费 | C17: 引用成本表 | D17: ='2-单车成本测算'!G34 -> 6773.76 | E17: ='2-单车成本测算'!H34 -> 6773.76 | F17: ='2-单车成本测算'!I34 -> 3386880 | G17: ='2-单车成本测算'!J34 -> 3386880 | H17: 元/月 | I17: 增值税及附加(9%)
B18: 成本合计 | C18: 引用成本表 | D18: ='2-单车成本测算'!G35 -> 71505.998 | E18: ='2-单车成本测算'!H35 -> 74036.093 | F18: ='2-单车成本测算'!I35 -> 35752999 | G18: ='2-单车成本测算'!J35 -> 37018047 | H18: 元/月 | I18: 总成本
B20: 三、毛利润
B21: 毛利润 | D21: =D6-D18 -> 3758.0022 | E21: =E6-E18 -> 1227.9067 | F21: =F6-F18 -> 1879001.1 | G21: =G6-G18 -> 613953.33 | H21: 元/月
B22: 毛利率 | D22: =D21/D6 -> 0.049930939 | E22: =E21/E6 -> 0.016314661 | F22: =F21/F6 -> 0.049930939 | G22: =G21/G6 -> 0.016314661 | H22: %
B23: 月净现金流 | C23: 毛利-利息 | D23: =D21-'2-单车成本测算'!E8/60 -> 3248.7453 | E23: =E21 -> 1227.9067 | F23: =F21-'2-单车成本测算'!E8*'1-基础参数'!C16/60 -> 1624372.6 | G23: =G21 -> 613953.33 | H23: 元/月 | I23: 不含本金
B24: 年化ROI | C24: 年净利/投资额 | D24: =IF(D6=0,0,D23*12/('2-单车成本测算'!$E$5+'2-单车成本测算'!$E$6+'2-单车成本测算'!$E$8)) -> 0.079471028 | H24: %
B26: 五、盈亏平衡分析
B27: 盈亏平衡运价 | C27: 成本/载重/趟数 | D27: =D18/('1-基础参数'!C9*'1-基础参数'!C12) -> 199.5145 | E27: =E18/('1-基础参数'!C9*'1-基础参数'!C12) -> 206.57392 | H27: 元/吨 | I27: 保本运价
B28: 盈亏平衡趟数 | C28: 成本/运价/载重 | D28: =D18/('1-基础参数'!C6*'1-基础参数'!C9) -> 10.640773 | E28: =E18/('1-基础参数'!C6*'1-基础参数'!C9) -> 11.017276 | H28: 趟/月 | I28: 保本趟数
B29: 盈亏平衡载重 | C29: 成本/运价/趟数 | D29: =D18/('1-基础参数'!C6*'1-基础参数'!C12) -> 30.40221 | E29: =E18/('1-基础参数'!C6*'1-基础参数'!C12) -> 31.477931 | H29: 吨 | I29: 保本载重
B30: 安全边际-运价 | C30: (当前-盈亏)/当前 | D30: =('1-基础参数'!$C$6-D$27)/'1-基础参数'!$C$6 -> 0.049930939 | E30: =('1-基础参数'!$C$6-E$27)/'1-基础参数'!$C$6 -> 0.016314661 | H30: % | I30: 价格下降空间
B31: 安全边际-趟数 | C31: (当前-盈亏)/当前 | D31: =('1-基础参数'!$C$12-D$28)/'1-基础参数'!$C$12 -> 0.049930939 | E31: =('1-基础参数'!$C$12-E$28)/'1-基础参数'!$C$12 -> 0.016314661 | H31: % | I31: 业务量下降空间

Sheet 3.5-资金清分
B2: 黄骅港电车物流项目 · 资金清分表
B4: 【计算规模】 | C4: ='1-基础参数'!C40 -> 1 | D4: 辆（自动引用基础参数计算车辆数）
B5: 说明：清分表逐层拆解单笔运费的资金去向，购置/租赁两列并排对比，校验行确认各层分账之和等于输入。
B7: 清分层级 / 项目 | C7: 清分规则说明 | D7: 购置模式（元/月） | E7: 租赁模式（元/月） | F7: 差异（租赁-购置） | G7: 占运费%（购置） | H7: 占运费%（租赁） | I7: 资金性质
B8: 【第0层】货主支付运费（资金入口）
B9: ① 月度运输总收入 | C9: 运价 × 载重 × 月趣数 × 计算车辆数 | D9: ='1-基础参数'!C6*'1-基础参数'!C9*'1-基础参数'!C12*'1-基础参数'!C40 -> 75264 | E9: ='1-基础参数'!C6*'1-基础参数'!C9*'1-基础参数'!C12*'1-基础参数'!C40 -> 75264 | F9: =E9-D9 -> 0 | G9: =IF(D9=0,"-",1) -> 1 | H9: =IF(E9=0,"-",1) -> 1 | I9: 运费收入
B10: ↓ 全额流入合同物流企业 | C10: 货主按账期付款，合同物流企业为总包方
B11: 【第1层】合同物流企业清分（总包方）
B12: ① 运费账期收益（留存） | C12: 运费 × 日利率 × 运费账期天数 | D12: =D9*'1-基础参数'!C25*'1-基础参数'!C22 -> 340.23452 | E12: =E9*'1-基础参数'!C25*'1-基础参数'!C22 -> 340.23452 | F12: =E12-D12 -> 0 | G12: =IF(D9=0,0,D12/D$9) -> 0.0045205479 | H12: =IF(E9=0,0,E12/E$9) -> 0.0045205479 | I12: 账期利差
B13: ② 车租账期收益（留存） | C13: 车租金 × 日利率 × 车租账期天数（购置=0） | D13: 0 | E13: ='2-单车成本测算'!H10*'1-基础参数'!C40*'1-基础参数'!C25*'1-基础参数'!C23 -> 67.619863 | F13: =E13-D13 -> 67.619863 | G13: =IF(D9=0,0,D13/D$9) -> 0 | H13: =IF(E9=0,0,E13/E$9) -> 0.00089843568 | I13: 账期利差
B14: ③ 平台信息服务费（支出） | C14: 转包金额 × 5‰ | D14: =(D9-D12-D13-D15)*'1-基础参数'!C26 -> 374.61883 | E14: =(E9-E12-E13-E15)*'1-基础参数'!C26 -> 299.48906 | F14: =E14-D14 -> -75.129766 | G14: =IF(D9=0,0,D14/D$9) -> 0.0049773973 | H14: =IF(E9=0,0,E14/E$9) -> 0.0039791808 | I14: 平台费
B15: ④ 车辆租赁费（支出） | C15: 车辆月租金 × 车辆数（购置=0） | D15: 0 | E15: ='2-单车成本测算'!H10*'1-基础参数'!C40 -> 14958.333 | F15: =E15-D15 -> 14958.333 | G15: =IF(D9=0,0,D15/D$9) -> 0 | H15: =IF(E9=0,0,E15/E$9) -> 0.19874486 | I15: 车辆成本
B16: ⑤ → 转包给物流服务公司 | C16: 运费总收入 - 车租 - 账期收益 | D16: =D9-D12-D13-D14-D15 -> 74549.147 | E16: =E9-E12-E13-E14-E15 -> 59598.323 | F16: =E16-D16 -> -14950.823 | G16: =IF(D9=0,0,D16/D$9) -> 0.99050205 | H16: =IF(E9=0,0,E16/E$9) -> 0.79185697 | I16: 分包款
B17: ★ 合同物流企业净收益 | C17: 账期利差收益（运费账期+车租账期） | D17: =D12+D13 -> 340.23452 | E17: =E12+E13 -> 407.85438 | F17: =E17-D17 -> 67.619863 | G17: =IF(D9=0,0,D17/D$9) -> 0.0045205479 | H17: =IF(E9=0,0,E17/E$9) -> 0.0054189836 | I17: 净收益
B18: 【校验】各项支出+净收益 = 运费总收入 | C18: 差异应为0 | D18: =D12+D13+D14+D15+D16-D9 -> 0 | E18: =E12+E13+E14+E15+E16-E9 -> 0 | F18: =E18-D18 -> 0 | G18: =IF(D9=0,0,D18/D$9) -> 0 | H18: =IF(E9=0,0,E18/E$9) -> 0 | I18: 校验
B20: ↓ D16/E16 流入物流服务公司，租赁模式下 E15 直接流入平台公司（车租链条） | C20: 同时：车租（租赁模式）直接流入平台公司
B21: 【第2层】物流服务公司清分（运营主体）
B22: 收入：来自合同物流转包款 | C22: 第1层⑤转包金额 | D22: =D16 -> 74549.147 | E22: =E16 -> 59598.323 | F22: =F16 -> -14950.823 | G22: =IF(D9=0,0,D22/D$9) -> 0.99050205 | H22: =IF(E9=0,0,E22/E$9) -> 0.79185697 | I22: 分包收入
B23: ① 扣：能源费用（支出） | C23: 月趟数×单趟能耗成本×车辆数 | D23: ='2-单车成本测算'!G21*'1-基础参数'!C40 -> 26936 | E23: ='2-单车成本测算'!H21*'1-基础参数'!C40 -> 26936 | F23: =E23-D23 -> 0 | G23: =IF(D9=0,0,D23/D$9) -> 0.3578869 | H23: =IF(E9=0,0,E23/E$9) -> 0.3578869 | I23: 能源成本
B24: ② 扣：维保费用（支出） | C24: 每公里维保费×月里程×车辆数 | D24: ='2-单车成本测算'!G28*'1-基础参数'!C40 -> 4368 | E24: ='2-单车成本测算'!H28*'1-基础参数'!C40 -> 4368 | F24: =E24-D24 -> 0 | G24: =IF(D9=0,0,D24/D$9) -> 0.058035714 | H24: =IF(E9=0,0,E24/E$9) -> 0.058035714 | I24: 维保成本
B25: ③ 扣：司机成本（硬性，先扣） | C25: 司机工资×人车比×车辆数 | D25: ='2-单车成本测算'!G24*'1-基础参数'!C40 -> 20000 | E25: ='2-单车成本测算'!H24*'1-基础参数'!C40 -> 20000 | F25: =E25-D25 -> 0 | G25: =IF(D9=0,0,D25/D$9) -> 0.26573129 | H25: =IF(E9=0,0,E25/E$9) -> 0.26573129 | I25: 人工成本
B26: ④ 扣：管理费用（硬性，先扣） | C26: 管理人员成本×车辆数 | D26: ='2-单车成本测算'!G32*'1-基础参数'!C40 -> 1000 | E26: ='2-单车成本测算'!H32*'1-基础参数'!C40 -> 1000 | F26: =E26-D26 -> 0 | G26: =IF(D9=0,0,D26/D$9) -> 0.013286565 | H26: =IF(E9=0,0,E26/E$9) -> 0.013286565 | I26: 管理成本
B27: ⑤ 净可分账额（分账基数） | C27: 转包收入 - 能源 - 维保 - 司机 - 管理 | D27: =D22-D23-D24-D25-D26 -> 22245.147 | E27: =E22-E23-E24-E25-E26 -> 7294.3232 | F27: =E27-D27 -> -14950.823 | G27: =IF(D9=0,0,D27/D$9) -> 0.29556158 | H27: =IF(E9=0,0,E27/E$9) -> 0.096916497 | I27: 分账基数
B28: ⑥ → 承运方分账（参数可调） | C28: ="净可分账额×"&TEXT('1-基础参数'!C33,"0%")&"（引用基础参数）" -> 净可分账额×55%（引用基础参数） | D28: =D27*'1-基础参数'!C33 -> 12234.831 | E28: =E27*'1-基础参数'!C33 -> 4011.8778 | F28: =E28-D28 -> -8222.9529 | G28: =IF(D9=0,0,D28/D$9) -> 0.16255887 | H28: =IF(E9=0,0,E28/E$9) -> 0.053304073 | I28: 承运分包款
B29: ★ 物流服务公司净收益留存 | C29: ="净可分账额×(1-"&TEXT('1-基础参数'!C33,"0%")&")留存" -> 净可分账额×(1-55%)留存 | D29: =D27*(1-'1-基础参数'!C33) -> 10010.316 | E29: =E27*(1-'1-基础参数'!C33) -> 3282.4454 | F29: =E29-D29 -> -6727.8705 | G29: =IF(D9=0,0,D29/D$9) -> 0.13300271 | H29: =IF(E9=0,0,E29/E$9) -> 0.043612424 | I29: 净收益
B30: 【校验】各项支出+净收益 = 转包收入 | C30: 差异应为0 | D30: =D23+D24+D25+D26+D28+D29-D22 -> 0 | E30: =E23+E24+E25+E26+E28+E29-E22 -> 0 | F30: =E30-D30 -> 0 | G30: =IF(D9=0,0,D30/D$9) -> 0 | H30: =IF(E9=0,0,E30/E$9) -> 0 | I30: 校验
B32: ↓ D28/E28 流入承运物流企业；能源费→充电服务商，由充电服务商向增值服务公司支付佣金；维保费→维保服务商，由维保服务商向增值服务公司支付佣金
B33: 2b. 平台公司清分（车赁收付链）
B34: 收入：车赁费来自合同物流企业 | C34: 第1层④车赁费（租赁模式=0） | D34: =D15 -> 0 | E34: =E15 -> 14958.333 | F34: =E34-D34 -> 14958.333 | G34: =IF(D9=0,0,D34/D$9) -> 0 | H34: =IF(E9=0,0,E34/E$9) -> 0.19874486 | I34: 车赁收入
B35: ① 支：车赁费→持车服务公司 | C35: 车赁费 - 200元/台溢价（平台公司留存） | D35: =IF(D34=0,0,D34-200*'1-基础参数'!C40) -> 0 | E35: =IF(E34=0,0,E34-200*'1-基础参数'!C40) -> 14758.333 | F35: =E35-D35 -> 14758.333 | G35: =IF(D9=0,0,D35/D$9) -> 0 | H35: =IF(E9=0,0,E35/E$9) -> 0.19608755 | I35: 车赁支出
B36: ★ 平台公司车赁净收益 | C36: 200元/台×车辆数（车赁溢价） | D36: =IF(D34=0,0,200*'1-基础参数'!C40) -> 0 | E36: =IF(E34=0,0,200*'1-基础参数'!C40) -> 200 | F36: =E36-D36 -> 200 | G36: =IF(D9=0,0,D36/D$9) -> 0 | H36: =IF(E9=0,0,E36/E$9) -> 0.0026573129 | I36: 净收益
B37: 【校验】转付持车服务公司+净收益 = 车赁收入 | C37: 差异应为0 | D37: =D35+D36-D34 -> 0 | E37: =E35+E36-E34 -> 0 | F37: =E37-D37 -> 0 | G37: =IF(D9=0,0,D37/D$9) -> 0 | H37: =IF(E9=0,0,E37/E$9) -> 0 | I37: 校验
B39: ↓ D35/E35 流入持车服务公司；平台公司留存200元/台溢价；购置模式无此分支
B43: 【第3层】承运物流企业清分（实际承运方）
B44: 收入：来自物流服务公司分包款 | C44: 第2层⑥承运方分账款（司机、管理已在第2层先扣） | D44: =D28 -> 12234.831 | E44: =E28 -> 4011.8778 | F44: =E44-D44 -> -8222.9529 | G44: =IF(D9=0,0,D44/D$9) -> 0.16255887 | H44: =IF(E9=0,0,E44/E$9) -> 0.053304073 | I44: 分包收入
B45: ① 扣：进场费用（支出） | C45: 进场费 × 车辆数 | D45: ='2-单车成本测算'!G33*'1-基础参数'!C40 -> 0 | E45: ='2-单车成本测算'!H33*'1-基础参数'!C40 -> 0 | F45: =E45-D45 -> 0 | G45: =IF(D9=0,0,D45/D$9) -> 0 | H45: =IF(E9=0,0,E45/E$9) -> 0 | I45: 进场成本
B46: ★ 承运物流企业经营利润 | C46: 分包收入 - 进场费（司机、管理已在第2层扣除） | D46: =D44-D45 -> 12234.831 | E46: =E44-E45 -> 4011.8778 | F46: =E46-D46 -> -8222.9529 | G46: =IF(D9=0,0,D46/D$9) -> 0.16255887 | H46: =IF(E9=0,0,E46/E$9) -> 0.053304073 | I46: 经营利润
B47: 【校验】进场费+经营利润 = 分包收入 | C47: 差异应为0 | D47: =D45+D46-D44 -> 0 | E47: =E45+E46-E44 -> 0 | F47: =E47-D47 -> 0 | G47: =IF(D9=0,0,D47/D$9) -> 0 | H47: =IF(E9=0,0,E47/E$9) -> 0 | I47: 校验
B49: ↓ 进场费→进场管理方；经营利润为承运方实际淨利。司机工资、管理费已由物流服务公司统一支付。
B51: 3b. 持车服务公司清分（车赁支付方）
B52: 收入：车赁来自平台公司 | C52: 2b①平台公司转付（车赁-200元溢价） | D52: =D35 -> 0 | E52: =E35 -> 14758.333 | F52: =E52-D52 -> 14758.333 | G52: =IF(D9=0,0,D52/D$9) -> 0 | H52: =IF(E9=0,0,E52/E$9) -> 0.19608755 | I52: 车赁收入
B53: ① 支：融资租赁成本→持车平台 | C53: 车辆购置月均摔销×(1+15%)×车辆数 | E53: ='2-单车成本测算'!G9*1.15*'1-基础参数'!C40 -> 11752.89 | F53: =E53-D53 -> 11752.89 | G53: =IF(D9=0,0,D53/D$9) -> 0 | H53: =IF(E9=0,0,E53/E$9) -> 0.15615553 | I53: 车赁支出
B54: ② 支：保险费→保险公司（购置模式） | C54: 保险小计×车辆数（购置模式有保险，租赁=0） | E54: ='2-单车成本测算'!G14*'1-基础参数'!C40 -> 2208.3333 | F54: =E54-D54 -> 2208.3333 | G54: =IF(D9=0,0,D54/D$9) -> 0 | H54: =IF(E9=0,0,E54/E$9) -> 0.029341164 | I54: 保险支出
B55: ★ 持车服务公司净收益 | C55: 车赁收入 - 融资租赁成本 - 保险 | D55: =D52-D53-D54 -> 0 | E55: =E52-E53-E54 -> 797.10984 | F55: =E55-D55 -> 797.10984 | G55: =IF(D9=0,0,D55/D$9) -> 0 | H55: =IF(E9=0,0,E55/E$9) -> 0.010590851 | I55: 净收益
B56: 【校验】持车平台+保险+净收益 = 车赁收入 | C56: 差异应为0 | D56: =D53+D54+D55-D52 -> 0 | E56: =E53+E54+E55-E52 -> 0 | F56: =E56-D56 -> 0 | G56: =IF(D9=0,0,D56/D$9) -> 0 | H56: =IF(E9=0,0,E56/E$9) -> 0 | I56: 校验
B58: ↓ 融资租赁成本 = 车辆购置月均摔销×115%（购置）/ H10全额（科目内含15%融资収益）（租赁）；保险费→保险公司；租赁模式平台200元溢价由持车服务公司承担
B61: 【第4层】渠道服务商清分（佣金支付方）
B62: 4a. 充电服务商清分
B63: 收入：来自物流服务公司能源费 | C63: 第2层①能源费用 | D63: =D23 -> 26936 | E63: =E23 -> 26936 | F63: =E63-D63 -> 0 | G63: =IF(D9=0,0,D63/D$9) -> 0.3578869 | H63: =IF(E9=0,0,E63/E$9) -> 0.3578869 | I63: 能源收入
B64: ① 支：基础电费→电力公司 | C64: 能源费 × 基础电费(0.67元) ÷ 电价(0.97元) | D64: =D63*('2-单车成本测算'!E15-'1-基础参数'!C27)/'2-单车成本测算'!E15 -> 18605.278 | E64: =E63*('2-单车成本测算'!E15-'1-基础参数'!C27)/'2-单车成本测算'!E15 -> 18605.278 | F64: =E64-D64 -> 0 | G64: =IF(D9=0,0,D64/D$9) -> 0.24720023 | H64: =IF(E9=0,0,E64/E$9) -> 0.24720023 | I64: 基础电费
B65: ② 支：渠道佣金→增値服务公司 | C65: 能源费 × 服务费(0.3元) ÷ 电价(0.97元) × 分涡10%(C28) | D65: =D63*'1-基础参数'!C27/'2-单车成本测算'!E15*'1-基础参数'!C28 -> 833.07216 | E65: =E63*'1-基础参数'!C27/'2-单车成本测算'!E15*'1-基础参数'!C28 -> 833.07216 | F65: =E65-D65 -> 0 | G65: =IF(D9=0,0,D65/D$9) -> 0.011068667 | H65: =IF(E9=0,0,E65/E$9) -> 0.011068667 | I65: 渠道佣金
B66: ★ 充电服务商净收益（服务费自留90%） | C66: 能源费 × 服务费(0.3元) ÷ 电价(0.97元) ×(1-分涡10%) | D66: =D63*'1-基础参数'!C27/'2-单车成本测算'!E15*(1-'1-基础参数'!C28) -> 7497.6495 | E66: =E63*'1-基础参数'!C27/'2-单车成本测算'!E15*(1-'1-基础参数'!C28) -> 7497.6495 | F66: =E66-D66 -> 0 | G66: =IF(D9=0,0,D66/D$9) -> 0.099618004 | H66: =IF(E9=0,0,E66/E$9) -> 0.099618004 | I66: 净收益
B67: 【校验】基础电费+佣金+净收益 = 能源费 | C67: 差异应为0 | D67: =D64+D65+D66-D63 -> 0 | E67: =E64+E65+E66-E63 -> 0 | F67: =E67-D67 -> 0 | G67: =IF(D9=0,0,D67/D$9) -> 0 | H67: =IF(E9=0,0,E67/E$9) -> 0 | I67: 校验
B69: 4b. 维保服务商清分
B70: 收入：来自物流服务公司维保费 | C70: 第2层②维保费用 | D70: =D24 -> 4368 | E70: =E24 -> 4368 | F70: =E70-D70 -> 0 | G70: =IF(D9=0,0,D70/D$9) -> 0.058035714 | H70: =IF(E9=0,0,E70/E$9) -> 0.058035714 | I70: 维保收入
B71: ① 支：净维保费→维保服务商 | C71: 维保费×(1-维保返佣率) | D71: =D70*(1-'1-基础参数'!C29) -> 3931.2 | E71: =E70*(1-'1-基础参数'!C29) -> 3931.2 | F71: =E71-D71 -> 0 | G71: =IF(D9=0,0,D71/D$9) -> 0.052232143 | H71: =IF(E9=0,0,E71/E$9) -> 0.052232143 | I71: 净维保费
B72: ② 支：渠道佣金→增值服务公司 | C72: 维保费×维保返佣率 | D72: =D70*'1-基础参数'!C29 -> 436.8 | E72: =E70*'1-基础参数'!C29 -> 436.8 | F72: =E72-D72 -> 0 | G72: =IF(D9=0,0,D72/D$9) -> 0.0058035714 | H72: =IF(E9=0,0,E72/E$9) -> 0.0058035714 | I72: 渠道佣金
B73: ★ 维保服务商净收益（0=过路） | C73: 收入 - 净维保 - 佣金 | D73: =D70-D71-D72 -> 0 | E73: =E70-E71-E72 -> 0 | F73: =E73-D73 -> 0 | G73: =IF(D9=0,0,D73/D$9) -> 0 | H73: =IF(E9=0,0,E73/E$9) -> 0 | I73: 净收益
B74: 【校验】净维保费+佣金 = 维保费 | C74: 差异应为0 | D74: =D71+D72-D70 -> 0 | E74: =E71+E72-E70 -> 0 | F74: =E74-D74 -> 0 | G74: =IF(D9=0,0,D74/D$9) -> 0 | H74: =IF(E9=0,0,E74/E$9) -> 0 | I74: 校验
B75: ↓ 净电费→电力公司；净维保费→维保服务商；充电服务费返佣 + 维保佣金 + 保险佣金 均→增值服务公司（BD渠道收益）
B77: 4c. 保险公司清分
B78: 收入：保险费来自持车服务公司 | C78: 3b②持车服务公司支付保险费（租赁=0） | D78: =D54 -> 0 | E78: =E54 -> 2208.3333 | F78: =E78-D78 -> 2208.3333 | G78: =IF(D9=0,0,D78/D$9) -> 0 | H78: =IF(E9=0,0,E78/E$9) -> 0.029341164 | I78: 保险收入
B79: ① 支：净保险费→保险承保方 | C79: 保险费×(1-保险渠道佣金率) | D79: =D78*(1-'1-基础参数'!C30) -> 0 | E79: =E78*(1-'1-基础参数'!C30) -> 1877.0833 | F79: =E79-D79 -> 1877.0833 | G79: =IF(D9=0,0,D79/D$9) -> 0 | H79: =IF(E9=0,0,E79/E$9) -> 0.024939989 | I79: 净保险费
B80: ② 支：渠道佣金→增值服务公司 | C80: 保险费×保险渠道佣金率（C30=15%） | D80: =D78*'1-基础参数'!C30 -> 0 | E80: =E78*'1-基础参数'!C30 -> 331.25 | F80: =E80-D80 -> 331.25 | G80: =IF(D9=0,0,D80/D$9) -> 0 | H80: =IF(E9=0,0,E80/E$9) -> 0.0044011745 | I80: 渠道佣金
B81: ★ 保险公司净收益（0=过路） | C81: 保险收入 - 净保险 - 佣金 | D81: =D78-D79-D80 -> 0 | E81: =E78-E79-E80 -> 0 | F81: =E81-D81 -> 0 | G81: =IF(D9=0,0,D81/D$9) -> 0 | H81: =IF(E9=0,0,E81/E$9) -> 0 | I81: 净收益
B82: 【校验】净保险+佣金 = 保险费 | C82: 差异应为0 | D82: =D79+D80-D78 -> 0 | E82: =E79+E80-E78 -> 0 | F82: =E82-D82 -> 0 | G82: =IF(D9=0,0,D82/D$9) -> 0 | H82: =IF(E9=0,0,E82/E$9) -> 0 | I82: 校验
B83: ↓ 净保险费→保险承保方；渠道佣金→增值服务公司（BD渠道收益）；租赁模式保险=0，这一分支无流量
B84: 【第5层】增値服务公司清分（BD渠道收益汇总）
B85: 收入①：充电渠道佣金（4a） | C85: 第4a层充电服务商支付佣金 | D85: =D65 -> 833.07216 | E85: =E65 -> 833.07216 | F85: =E85-D85 -> 0 | G85: =IF(D9=0,0,D85/D$9) -> 0.011068667 | H85: =IF(E9=0,0,E85/E$9) -> 0.011068667 | I85: 充电佣金
B86: 收入②：维保渠道佣金（4b） | C86: 第4b层维保服务商支付佣金 | D86: =D72 -> 436.8 | E86: =E72 -> 436.8 | F86: =E86-D86 -> 0 | G86: =IF(D9=0,0,D86/D$9) -> 0.0058035714 | H86: =IF(E9=0,0,E86/E$9) -> 0.0058035714 | I86: 维保佣金
B87: 收入③：保险渠道佣金（4c） | C87: 第4c层保险公司支付佣金 | D87: =D80 -> 0 | E87: =E80 -> 331.25 | F87: =E87-D87 -> 331.25 | G87: =IF(D9=0,0,D87/D$9) -> 0 | H87: =IF(E9=0,0,E87/E$9) -> 0.0044011745 | I87: 保险佣金
B88: 小计：三类佣金合计 | C88: 充电佣金 + 维保佣金 + 保险佣金 | D88: =D85+D86+D87 -> 1269.8722 | E88: =E85+E86+E87 -> 1601.1222 | F88: =E88-D88 -> 331.25 | G88: =IF(D9=0,0,D88/D$9) -> 0.016872239 | H88: =IF(E9=0,0,E88/E$9) -> 0.021273413 | I88: 佣金合计
B89: ① 支：向平台公司返佣（BD成本） | C89: 三类佣金合计 × 返佣率(C34=25%) | D89: =D88*'1-基础参数'!$C$34 -> 317.46804 | E89: =E88*'1-基础参数'!$C$34 -> 400.28054 | F89: =E89-D89 -> 82.8125 | G89: =IF(D9=0,0,D89/D$9) -> 0.0042180596 | H89: =IF(E9=0,0,E89/E$9) -> 0.0053183533 | I89: 返佣支出
B90: ★ 增値服务公司净收益 | C90: 三类佣金合计 × (1 - 返佣率25%) | D90: =D88*(1-'1-基础参数'!$C$34) -> 952.40412 | E90: =E88*(1-'1-基础参数'!$C$34) -> 1200.8416 | F90: =E90-D90 -> 248.4375 | G90: =IF(D9=0,0,D90/D$9) -> 0.012654179 | H90: =IF(E9=0,0,E90/E$9) -> 0.01595506 | I90: 净收益
B91: 【校验】返佣 + 净收益 = 佣金合计 | C91: 差异应为0 | D91: =D89+D90-D88 -> 0 | E91: =E89+E90-E88 -> 0 | F91: =E91-D91 -> 0 | G91: =IF(D9=0,0,D91/D$9) -> 0 | H91: =IF(E9=0,0,E91/E$9) -> 0 | I91: 校验
B92: ↓ 增値服务公司汇聗65元(充电)、437元(维保)、保险佣金(租赁模式)3类BD渠道收益；按C34比例返佣平台公司，自身留存(1-C34)

Sheet 4-相关方收益分配
B1: 相关方收益分配表
B2: 说明：本表基于【3.5-资金清分】逐层拆解各参与方的收入、支出与净收益，购置/租赁两列并排对比。
B5: 参与方 | C5: 收支项目 | D5: 购置-收入 （元/月） | E5: 购置-支出 （元/月） | F5: 购置-净收益 （元/月） | G5: 租赁-收入 （元/月） | H5: 租赁-支出 （元/月） | I5: 租赁-净收益 （元/月） | J5: 备注
B8: 1. 货主企业 | C8: 支付运费 | D8: ='3.5-资金清分'!D9 -> 75264 | E8: ='3.5-资金清分'!D9 -> 75264 | F8: 0 | G8: ='3.5-资金清分'!E9 -> 75264 | H8: ='3.5-资金清分'!E9 -> 75264 | I8: 0 | J8: 货主付款，无收益
B9: 2. 合同物流企业 | C9: 运费收入 | D9: ='3.5-资金清分'!D9 -> 75264 | G9: ='3.5-资金清分'!E9 -> 75264 | J9: 从货主收款
C10: 运费账期利息（留存） | E10: ='3.5-资金清分'!D12 -> 340.23452 | H10: ='3.5-资金清分'!E12 -> 340.23452 | J10: 运费账期利差收益
C11: 车租账期利息（留存） | E11: 0 | H11: ='3.5-资金清分'!E13 -> 67.619863 | J11: 租赁账期利差收益（购置=0）
C12: 平台信息服务费（支出） | E12: ='3.5-资金清分'!D14 -> 374.61883 | H12: ='3.5-资金清分'!E14 -> 299.48906 | J12: 向平台公司支付，按转包金额×5‰
C13: 车辆租赁费（支出） | E13: 0 | H13: ='3.5-资金清分'!E15 -> 14958.333 | J13: 向平台公司支付租赁车辆（购置=0）
C14: 转包款（支出） | E14: ='3.5-资金清分'!D16 -> 74549.147 | H14: ='3.5-资金清分'!E16 -> 59598.323 | J14: 向物流服务公司支付转包款
C15: 小计 | D15: ='3.5-资金清分'!D9 -> 75264 | E15: ='3.5-资金清分'!D14+'3.5-资金清分'!D16 -> 74923.765 | F15: ='3.5-资金清分'!D17 -> 340.23452 | G15: ='3.5-资金清分'!E9 -> 75264 | H15: ='3.5-资金清分'!E14+'3.5-资金清分'!E15+'3.5-资金清分'!E16 -> 74856.146 | I15: ='3.5-资金清分'!E17 -> 407.85438 | J15: 净收益=运费账期利息+车租账期利息
B16: 3. 物流服务公司 | C16: 转包款收入 | D16: ='3.5-资金清分'!D22 -> 74549.147 | G16: ='3.5-资金清分'!E22 -> 59598.323 | J16: 来自合同物流企业转包
C17: 能源费（支出） | E17: ='3.5-资金清分'!D23 -> 26936 | H17: ='3.5-资金清分'!E23 -> 26936 | J17: 支付充电服务商
C18: 维保费（支出） | E18: ='3.5-资金清分'!D24 -> 4368 | H18: ='3.5-资金清分'!E24 -> 4368 | J18: 支付维保服务商
C19: 司机成本（硬性支出） | E19: ='3.5-资金清分'!D25 -> 20000 | H19: ='3.5-资金清分'!E25 -> 20000 | J19: 平台代付司机薪酬
C20: 管理费用（硬性支出） | E20: ='3.5-资金清分'!D26 -> 1000 | H20: ='3.5-资金清分'!E26 -> 1000 | J20: 管理人员成本
C21: 承运方分包款（支出） | E21: ='3.5-资金清分'!D28 -> 12234.831 | H21: ='3.5-资金清分'!E28 -> 4011.8778 | J21: 按可分账额×55%支付承运方
C22: 小计 | D22: ='3.5-资金清分'!D22 -> 74549.147 | E22: ='3.5-资金清分'!D23+'3.5-资金清分'!D24+'3.5-资金清分'!D25+'3.5-资金清分'!D26+'3.5-资金清分'!D28 -> 64538.831 | F22: ='3.5-资金清分'!D29 -> 10010.316 | G22: ='3.5-资金清分'!E22 -> 59598.323 | H22: ='3.5-资金清分'!E23+'3.5-资金清分'!E24+'3.5-资金清分'!E25+'3.5-资金清分'!E26+'3.5-资金清分'!E28 -> 56315.878 | I22: ='3.5-资金清分'!E29 -> 3282.4454 | J22: 净收益=可分账额×45%留存
B23: 4. 承运物流企业 | C23: 分包款收入 | D23: ='3.5-资金清分'!D44 -> 12234.831 | G23: ='3.5-资金清分'!E44 -> 4011.8778 | J23: 来自物流服务公司分包（55%可分账额）
C24: 进场费用（支出） | E24: ='3.5-资金清分'!D45 -> 0 | H24: ='3.5-资金清分'!E45 -> 0 | J24: 向进场管理方支付
C25: 小计 | D25: ='3.5-资金清分'!D44 -> 12234.831 | E25: ='3.5-资金清分'!D45 -> 0 | F25: ='3.5-资金清分'!D46 -> 12234.831 | G25: ='3.5-资金清分'!E44 -> 4011.8778 | H25: ='3.5-资金清分'!E45 -> 0 | I25: ='3.5-资金清分'!E46 -> 4011.8778 | J25: 净收益=分包款-进场费
B26: 5. 平台公司 | C26: 车赁费收入 | D26: 0 | G26: ='3.5-资金清分'!E34 -> 14958.333 | J26: 合同物流企业车赁费（购置=0）
C27: 平台信息服务费收入 | D27: ='3.5-资金清分'!D14 -> 374.61883 | G27: ='3.5-资金清分'!E14 -> 299.48906 | J27: 分包金额×5‰
C28: 增値服务公司返佣收入 | D28: ='3.5-资金清分'!D89 -> 317.46804 | G28: ='3.5-资金清分'!E89 -> 400.28054 | J28: BD返佣平台
C29: 车赁转付持车服务公司（支出） | D29: 0 | G29: ='3.5-资金清分'!E35 -> 14758.333 | J29: 购置=0
C30: 小计 | D30: ='3.5-资金清分'!D14+'3.5-资金清分'!D89 -> 692.08687 | E30: 0 | F30: ='3.5-资金清分'!D14+'3.5-资金清分'!D89 -> 692.08687 | G30: ='3.5-资金清分'!E34+'3.5-资金清分'!E14+'3.5-资金清分'!E89 -> 15658.103 | H30: ='3.5-资金清分'!E35 -> 14758.333 | I30: ='3.5-资金清分'!E36+'3.5-资金清分'!E14+'3.5-资金清分'!E89 -> 899.7696 | J30: 购置=信息费+返佣；租赁另加车赁溢价+账期利
B31: 6. 持车服务公司 | C31: 车赁收入（平台转付） | D31: 0 | G31: ='3.5-资金清分'!E52 -> 14758.333 | J31: 购置=0
C32: 融资租赁成本→持车平台（支出） | D32: ='3.5-资金清分'!D53 -> 0 | G32: ='3.5-资金清分'!E53 -> 11752.89 | J32: 购置=摆销×115%；租赁=H10全额
C33: 保险费→保险公司（支出） | D33: ='3.5-资金清分'!D54 -> 0 | G33: ='3.5-资金清分'!E54 -> 2208.3333 | J33: 购置有保险，租赁=0
C34: 小计 | D34: ='3.5-资金清分'!D52 -> 0 | E34: ='3.5-资金清分'!D53+'3.5-资金清分'!D54 -> 0 | F34: ='3.5-资金清分'!D55 -> 0 | G34: ='3.5-资金清分'!E52 -> 14758.333 | H34: ='3.5-资金清分'!E53+'3.5-资金清分'!E54 -> 13961.223 | I34: ='3.5-资金清分'!E55 -> 797.10984 | J34: 购置=摆销-融资-保险
B35: 7. 持车平台 | C35: 融资租赁收入 | D35: ='3.5-资金清分'!D53 -> 0 | G35: ='3.5-资金清分'!E53 -> 11752.89 | J35: 持车服务公司支付
C36: 车辆融资本金成本（支出） | D36: ='3.5-资金清分'!D53/1.15 -> 0 | G36: ='3.5-资金清分'!E53/1.15 -> 10219.904 | J36: 融资本金=收入/1.15
C37: 小计 | D37: ='3.5-资金清分'!D53 -> 0 | E37: ='3.5-资金清分'!D53/1.15 -> 0 | F37: ='3.5-资金清分'!D53*0.15/1.15 -> 0 | G37: ='3.5-资金清分'!E53 -> 11752.89 | H37: ='3.5-资金清分'!E53/1.15 -> 10219.904 | I37: ='3.5-资金清分'!E53*0.15/1.15 -> 1532.9857 | J37: 净收益=融资收入×15%/1.15
B38: 8. 充电服务商 | C38: 能源费收入 | D38: ='3.5-资金清分'!D63 -> 26936 | G38: ='3.5-资金清分'!E63 -> 26936 | J38: 来自物流服务公司
C39: 基础电费→电力公司（支出） | E39: ='3.5-资金清分'!D64 -> 18605.278 | H39: ='3.5-资金清分'!E64 -> 18605.278 | J39: 能源费×0.67/0.97
C40: 渠道佣金→增値公司（支出） | E40: ='3.5-资金清分'!D65 -> 833.07216 | H40: ='3.5-资金清分'!E65 -> 833.07216 | J40: 服务费×0.3/0.97×10%
C41: 小计 | D41: ='3.5-资金清分'!D63 -> 26936 | E41: ='3.5-资金清分'!D64+'3.5-资金清分'!D65 -> 19438.351 | F41: ='3.5-资金清分'!D66 -> 7497.6495 | G41: ='3.5-资金清分'!E63 -> 26936 | H41: ='3.5-资金清分'!E64+'3.5-资金清分'!E65 -> 19438.351 | I41: ='3.5-资金清分'!E66 -> 7497.6495 | J41: 净收益=服务费自喐90%
B42: 9. 维保服务商 | C42: 维保费收入 | D42: ='3.5-资金清分'!D70 -> 4368 | G42: ='3.5-资金清分'!E70 -> 4368 | J42: 来自物流服务公司
C43: 净维保费+渠道佣金（支出） | E43: ='3.5-资金清分'!D71+'3.5-资金清分'!D72 -> 4368 | H43: ='3.5-资金清分'!E71+'3.5-资金清分'!E72 -> 4368 | J43: 过路=0
C44: 小计 | D44: ='3.5-资金清分'!D70 -> 4368 | E44: ='3.5-资金清分'!D71+'3.5-资金清分'!D72 -> 4368 | F44: ='3.5-资金清分'!D73 -> 0 | G44: ='3.5-资金清分'!E70 -> 4368 | H44: ='3.5-资金清分'!E71+'3.5-资金清分'!E72 -> 4368 | I44: ='3.5-资金清分'!E73 -> 0 | J44: 过路企业，净收益=0
B45: 10. 保险服务商 | C45: 保险费收入 | D45: ='3.5-资金清分'!D78 -> 0 | G45: ='3.5-资金清分'!E78 -> 2208.3333 | J45: 持车服务公司支付
C46: 净保险费+渠道佣金（支出） | E46: ='3.5-资金清分'!D79+'3.5-资金清分'!D80 -> 0 | H46: ='3.5-资金清分'!E79+'3.5-资金清分'!E80 -> 2208.3333 | J46: 过路=0
C47: 小计 | D47: ='3.5-资金清分'!D78 -> 0 | E47: ='3.5-资金清分'!D79+'3.5-资金清分'!D80 -> 0 | F47: ='3.5-资金清分'!D81 -> 0 | G47: ='3.5-资金清分'!E78 -> 2208.3333 | H47: ='3.5-资金清分'!E79+'3.5-资金清分'!E80 -> 2208.3333 | I47: ='3.5-资金清分'!E81 -> 0 | J47: 购置=0，租赁有流量
B48: 11. 增値服务公司 | C48: 充电/维保/保险佣金收入 | D48: ='3.5-资金清分'!D88 -> 1269.8722 | G48: ='3.5-资金清分'!E88 -> 1601.1222 | J48: 4a+4b+4c三类BD佣金
C49: 返佣平台公司（支出） | E49: ='3.5-资金清分'!D89 -> 317.46804 | H49: ='3.5-资金清分'!E89 -> 400.28054 | J49: 三类佣金合计×25%
C50: 小计 | D50: ='3.5-资金清分'!D88 -> 1269.8722 | E50: ='3.5-资金清分'!D89 -> 317.46804 | F50: ='3.5-资金清分'!D90 -> 952.40412 | G50: ='3.5-资金清分'!E88 -> 1601.1222 | H50: ='3.5-资金清分'!E89 -> 400.28054 | I50: ='3.5-资金清分'!E90 -> 1200.8416 | J50: 净收益=三类佣金×75%

Sheet 5-资金流向图
B2: 资金流向分析表
B3: 说明：本表基于【3.5-资金清分】汇总各层级资金流转金额，购置/租赁模式分列对比。
B5: 一、主要资金流向（月度）
B7: 序号 | C7: 资金流向 | D7: 购置模式金额（元/月） | E7: 租赁模式金额（元/月） | F7: 资金性质 | G7: 说明
B8: 1 | C8: 货主 → 合同物流企业 | D8: ='3.5-资金清分'!D9 -> 75264 | E8: ='3.5-资金清分'!E9 -> 75264 | F8: 运费 | G8: 货主支付全部运输费用
B9: 2 | C9: 合同物流 → 物流服务公司 | D9: ='3.5-资金清分'!D16 -> 74549.147 | E9: ='3.5-资金清分'!E16 -> 59598.323 | F9: 转包运费 | G9: 扣除账期收益后支付转包款
B10: 3 | C10: 合同物流 → 平台公司（车赁费） | D10: =0 -> 0 | E10: ='3.5-资金清分'!E15 -> 14958.333 | F10: 租赁费 | G10: 车辆租赁费用（购置模式=0）
B11: 4 | C11: 合同物流 → 平台公司（信息费） | D11: ='3.5-资金清分'!D14 -> 374.61883 | E11: ='3.5-资金清分'!E14 -> 299.48906 | F11: 信息服务费 | G11: 转包金额x5‰
B12: 5 | C12: 物流服务 → 承运物流企业 | D12: ='3.5-资金清分'!D28 -> 12234.831 | E12: ='3.5-资金清分'!E28 -> 4011.8778 | F12: 承运费 | G12: 按可分账额x55%支付
B13: 6 | C13: 物流服务 → 充电服务商 | D13: ='3.5-资金清分'!D23 -> 26936 | E13: ='3.5-资金清分'!E23 -> 26936 | F13: 能源费 | G13: 充电费用
B14: 7 | C14: 物流服务 → 维保服务商 | D14: ='3.5-资金清分'!D24 -> 4368 | E14: ='3.5-资金清分'!E24 -> 4368 | F14: 维保费 | G14: 车辆维修保养费用
B15: 8 | C15: 物流服务 → 承运方（司机成本） | D15: ='3.5-资金清分'!D25 -> 20000 | E15: ='3.5-资金清分'!E25 -> 20000 | F15: 工资 | G15: 司机薪酬（硬性成本）
B16: 9 | C16: 物流服务 → 承运方（管理费用） | D16: ='3.5-资金清分'!D26 -> 1000 | E16: ='3.5-资金清分'!E26 -> 1000 | F16: 管理费 | G16: 管理人员成本（硬性成本）
B17: 10 | C17: 平台公司 → 持车服务公司 | D17: =0 -> 0 | E17: ='3.5-资金清分'!E35 -> 14758.333 | F17: 租赁费 | G17: 扣除200元/台溢价后转付（购置=0）
B18: 11 | C18: 持车服务 → 持车平台（融资租赁） | D18: ='3.5-资金清分'!D53 -> 0 | E18: ='3.5-资金清分'!E53 -> 11752.89 | F18: 融资租赁成本 | G18: 车辆购置摸销xd7115%
B19: 12 | C19: 持车服务 → 保险服务商 | D19: ='3.5-资金清分'!D54 -> 0 | E19: ='3.5-资金清分'!E54 -> 2208.3333 | F19: 保险费 | G19: 车辆保险费用
B20: 13 | C20: 充电服务商 → 电力公司 | D20: ='3.5-资金清分'!D64 -> 18605.278 | E20: ='3.5-资金清分'!E64 -> 18605.278 | F20: 电费 | G20: 基础电费成本
B21: 14 | C21: 服务商 → 增值服务公司（三类BD佣金） | D21: ='3.5-资金清分'!D88 -> 1269.8722 | E21: ='3.5-资金清分'!E88 -> 1601.1222 | F21: 返佣 | G21: 充电/维保/保险三类BD佣金合计
B22: 15 | C22: 增值服务公司 → 平台公司（返佣） | D22: ='3.5-资金清分'!D89 -> 317.46804 | E22: ='3.5-资金清分'!E89 -> 400.28054 | F22: 返佣 | G22: 三类BD佣金xd725%返赠平台
B25: 二、各参与方月度净收益汇总
B27: 序号 | C27: 参与方 | D27: 购置模式净收益（元/月） | E27: 租赁模式净收益（元/月） | F27: 购置占总利润% | G27: 租赁占总利润% | H27: 业务角色
B28: 1 | C28: 合同物流企业 | D28: ='4-相关方收益分配'!F15 -> 340.23452 | E28: ='4-相关方收益分配'!I15 -> 407.85438 | F28: =IF(D$38=0,"-",D28/D$38) -> 0.01072364 | G28: =IF(E$38=0,"-",E28/E$38) -> 0.02077653 | H28: BD渠道
B29: 2 | C29: 物流服务公司 | D29: ='4-相关方收益分配'!F22 -> 10010.316 | E29: ='4-相关方收益分配'!I22 -> 3282.4454 | F29: =IF(D$38=0,"-",D29/D$38) -> 0.31550892 | G29: =IF(E$38=0,"-",E29/E$38) -> 0.16721122 | H29: BD渠道
B30: 3 | C30: 承运物流企业 | D30: ='4-相关方收益分配'!F25 -> 12234.831 | E30: ='4-相关方收益分配'!I25 -> 4011.8778 | F30: =IF(D$38=0,"-",D30/D$38) -> 0.38562201 | G30: =IF(E$38=0,"-",E30/E$38) -> 0.20436927 | H30: 实际承运
B31: 4 | C31: 平台公司 | D31: ='4-相关方收益分配'!F30 -> 692.08687 | E31: ='4-相关方收益分配'!I30 -> 899.7696 | F31: =IF(D$38=0,"-",D31/D$38) -> 0.021813455 | G31: =IF(E$38=0,"-",E31/E$38) -> 0.045835208 | H31: 平台运营方
B32: 5 | C32: 持车服务公司 | D32: ='4-相关方收益分配'!F34 -> 0 | E32: ='4-相关方收益分配'!I34 -> 797.10984 | F32: =IF(D$38=0,"-",D32/D$38) -> 0 | G32: =IF(E$38=0,"-",E32/E$38) -> 0.040605612 | H32: 资产持有
B33: 6 | C33: 持车平台 | D33: ='4-相关方收益分配'!F37 -> 0 | E33: ='4-相关方收益分配'!I37 -> 1532.9857 | F33: =IF(D$38=0,"-",D33/D$38) -> 0 | G33: =IF(E$38=0,"-",E33/E$38) -> 0.078091899 | H33: 融资持车
B34: 7 | C34: 充电服务商 | D34: ='4-相关方收益分配'!F41 -> 7497.6495 | E34: ='4-相关方收益分配'!I41 -> 7497.6495 | F34: =IF(D$38=0,"-",D34/D$38) -> 0.23631375 | G34: =IF(E$38=0,"-",E34/E$38) -> 0.38193814 | H34: 能源供应
B35: 8 | C35: 维保服务商 | D35: ='4-相关方收益分配'!F44 -> 0 | E35: ='4-相关方收益分配'!I44 -> 0 | F35: =IF(D$38=0,"-",D35/D$38) -> 0 | G35: =IF(E$38=0,"-",E35/E$38) -> 0 | H35: 维保服务
B36: 9 | C36: 保险服务商 | D36: ='4-相关方收益分配'!F47 -> 0 | E36: ='4-相关方收益分配'!I47 -> 0 | F36: =IF(D$38=0,"-",D36/D$38) -> 0 | G36: =IF(E$38=0,"-",E36/E$38) -> 0 | H36: 保险服务
B37: 10 | C37: 增值服务公司 | D37: ='4-相关方收益分配'!F50 -> 952.40412 | E37: ='4-相关方收益分配'!I50 -> 1200.8416 | F37: =IF(D$38=0,"-",D37/D$38) -> 0.030018233 | G37: =IF(E$38=0,"-",E37/E$38) -> 0.061172133 | H37: BD渠道
C38: 合计 | D38: =SUM(D28:D37) -> 31727.522 | E38: =SUM(E28:E37) -> 19630.534 | F38: 1 | G38: 1
B41: 三、三大BD渠道角色收益对比
B43: BD角色 | C43: 收益来源 | D43: 购置模式净收益（元/月） | E43: 租赁模式净收益（元/月） | F43: 购置占BD合计% | G43: 租赁占BD合计% | H43: 主要业务
B44: 物流服务公司 | C44: 运费分账+账期收益 | D44: ='4-相关方收益分配'!F22 -> 10010.316 | E44: ='4-相关方收益分配'!I22 -> 3282.4454 | F44: =IF(D$47=0,"-",D44/D$47) -> 0.91312338 | G44: =IF(E$47=0,"-",E44/E$47) -> 0.62162854 | H44: 物流运输渠道
B45: 持车服务公司 | C45: 车赁费收入-融资租赁-保险 | D45: ='4-相关方收益分配'!F34 -> 0 | E45: ='4-相关方收益分配'!I34 -> 797.10984 | F45: =IF(D$47=0,"-",D45/D$47) -> 0 | G45: =IF(E$47=0,"-",E45/E$47) -> 0.15095643 | H45: 车辆资产渠道
B46: 增值服务公司 | C46: 充电/维保/保险三类BD佣金×75% | D46: ='4-相关方收益分配'!F50 -> 952.40412 | E46: ='4-相关方收益分配'!I50 -> 1200.8416 | F46: =IF(D$47=0,"-",D46/D$47) -> 0.086876625 | G46: =IF(E$47=0,"-",E46/E$47) -> 0.22741503 | H46: 增值服务渠道
B47: BD渠道合计 | D47: =SUM(D44:D46) -> 10962.72 | E47: =SUM(E44:E46) -> 5280.3969 | F47: 1 | G47: 1
B48: 备注 | C48: 购置模式持车服务公司收益=0（无车赁）；租赁模式三大BD渠道均可获益。平台公司为平台运营方（非纯商业性BD渠道），单独列示于区块二。

Sheet 6-敏感性分析
B2: 关键参数敏感性分析
B3: 说明：本表模拟关键参数变动对各参与方收益的影响，基于单车购置模式。所有公式独立计算，修改基础参数后自动刷新。
B5: 一、运价敏感性分析
B6: 变动幅度 | C6: 运价 （元/吨） | D6: 月收入 （元） | E6: 毛利润 （元） | F6: 毛利率 | G6: 物流服务 公司净收益 | H6: 承运物流 企业净收益 | I6: 平台公司 净收益 | J6: 全参与方 净收益合计
B7: -0.3 | C7: ='1-基础参数'!$C$6*(1+B7) -> 147 | D7: =C7*'1-基础参数'!$C$9*'1-基础参数'!$C$12 -> 52684.8 | E7: =D7-'2-单车成本测算'!$G$35 -> -18821.198 | F7: =IF(D7=0,0,E7/D7) -> -0.35724152 | G7: =((D7-D7*'1-基础参数'!$C$25*'1-基础参数'!$C$22)*(1-'1-基础参数'!$C$26)-'2-单车成本测算'!$G$21-'2-单车成本测算'!$G$28-'2-单车成本测算'!$G$24-'2-单车成本测算'!$G$32)*(1-'1-基础参数'!$C$33) -> -53.818805 | H7: =((D7-D7*'1-基础参数'!$C$25*'1-基础参数'!$C$22)*(1-'1-基础参数'!$C$26)-'2-单车成本测算'!$G$21-'2-单车成本测算'!$G$28-'2-单车成本测算'!$G$24-'2-单车成本测算'!$G$32)*'1-基础参数'!$C$33 -> -65.778539 | I7: =(D7-D7*'1-基础参数'!$C$25*'1-基础参数'!$C$22)*'1-基础参数'!$C$26+('2-单车成本测算'!$G$21*'1-基础参数'!$C$27/'2-单车成本测算'!$E$15*'1-基础参数'!$C$28+'2-单车成本测算'!$G$28*'1-基础参数'!$C$29)*'1-基础参数'!$C$34 -> 579.70122 | J7: =D7*'1-基础参数'!$C$25*'1-基础参数'!$C$22+G7+H7+I7+'2-单车成本测算'!$G$21*'1-基础参数'!$C$27/'2-单车成本测算'!$E$15*(1-'1-基础参数'!$C$28)+('2-单车成本测算'!$G$21*'1-基础参数'!$C$27/'2-单车成本测算'!$E$15*'1-基础参数'!$C$28+'2-单车成本测算'!$G$28*'1-基础参数'!$C$29)*(1-'1-基础参数'!$C$34) -> 9148.3216
B8: -0.2 | C8: ='1-基础参数'!$C$6*(1+B8) -> 168 | D8: =C8*'1-基础参数'!$C$9*'1-基础参数'!$C$12 -> 60211.2 | E8: =D8-'2-单车成本测算'!$G$35 -> -11294.798 | F8: =IF(D8=0,0,E8/D8) -> -0.18758633 | G8: =((D8-D8*'1-基础参数'!$C$25*'1-基础参数'!$C$22)*(1-'1-基础参数'!$C$26)-'2-单车成本测算'!$G$21-'2-单车成本测算'!$G$28-'2-单车成本测算'!$G$24-'2-单车成本测算'!$G$32)*(1-'1-基础参数'!$C$33) -> 3300.8928 | H8: =((D8-D8*'1-基础参数'!$C$25*'1-基础参数'!$C$22)*(1-'1-基础参数'!$C$26)-'2-单车成本测算'!$G$21-'2-单车成本测算'!$G$28-'2-单车成本测算'!$G$24-'2-单车成本测算'!$G$32)*'1-基础参数'!$C$33 -> 4034.4245 | I8: =(D8-D8*'1-基础参数'!$C$25*'1-基础参数'!$C$22)*'1-基础参数'!$C$26+('2-单车成本测算'!$G$21*'1-基础参数'!$C$27/'2-单车成本测算'!$E$15*'1-基础参数'!$C$28+'2-单车成本测算'!$G$28*'1-基础参数'!$C$29)*'1-基础参数'!$C$34 -> 617.1631 | J8: =D8*'1-基础参数'!$C$25*'1-基础参数'!$C$22+G8+H8+I8+'2-单车成本测算'!$G$21*'1-基础参数'!$C$27/'2-单车成本测算'!$E$15*(1-'1-基础参数'!$C$28)+('2-单车成本测算'!$G$21*'1-基础参数'!$C$27/'2-单车成本测算'!$E$15*'1-基础参数'!$C$28+'2-单车成本测算'!$G$28*'1-基础参数'!$C$29)*(1-'1-基础参数'!$C$34) -> 16674.722
B9: -0.1 | C9: ='1-基础参数'!$C$6*(1+B9) -> 189 | D9: =C9*'1-基础参数'!$C$9*'1-基础参数'!$C$12 -> 67737.6 | E9: =D9-'2-单车成本测算'!$G$35 -> -3768.3978 | F9: =IF(D9=0,0,E9/D9) -> -0.05563229 | G9: =((D9-D9*'1-基础参数'!$C$25*'1-基础参数'!$C$22)*(1-'1-基础参数'!$C$26)-'2-单车成本测算'!$G$21-'2-单车成本测算'!$G$28-'2-单车成本测算'!$G$24-'2-单车成本测算'!$G$32)*(1-'1-基础参数'!$C$33) -> 6655.6044 | H9: =((D9-D9*'1-基础参数'!$C$25*'1-基础参数'!$C$22)*(1-'1-基础参数'!$C$26)-'2-单车成本测算'!$G$21-'2-单车成本测算'!$G$28-'2-单车成本测算'!$G$24-'2-单车成本测算'!$G$32)*'1-基础参数'!$C$33 -> 8134.6276 | I9: =(D9-D9*'1-基础参数'!$C$25*'1-基础参数'!$C$22)*'1-基础参数'!$C$26+('2-单车成本测算'!$G$21*'1-基础参数'!$C$27/'2-单车成本测算'!$E$15*'1-基础参数'!$C$28+'2-单车成本测算'!$G$28*'1-基础参数'!$C$29)*'1-基础参数'!$C$34 -> 654.62499 | J9: =D9*'1-基础参数'!$C$25*'1-基础参数'!$C$22+G9+H9+I9+'2-单车成本测算'!$G$21*'1-基础参数'!$C$27/'2-单车成本测算'!$E$15*(1-'1-基础参数'!$C$28)+('2-单车成本测算'!$G$21*'1-基础参数'!$C$27/'2-单车成本测算'!$E$15*'1-基础参数'!$C$28+'2-单车成本测算'!$G$28*'1-基础参数'!$C$29)*(1-'1-基础参数'!$C$34) -> 24201.122
B10: 0 | C10: ='1-基础参数'!$C$6*(1+B10) -> 210 | D10: =C10*'1-基础参数'!$C$9*'1-基础参数'!$C$12 -> 75264 | E10: =D10-'2-单车成本测算'!$G$35 -> 3758.0022 | F10: =IF(D10=0,0,E10/D10) -> 0.049930939 | G10: =((D10-D10*'1-基础参数'!$C$25*'1-基础参数'!$C$22)*(1-'1-基础参数'!$C$26)-'2-单车成本测算'!$G$21-'2-单车成本测算'!$G$28-'2-单车成本测算'!$G$24-'2-单车成本测算'!$G$32)*(1-'1-基础参数'!$C$33) -> 10010.316 | H10: =((D10-D10*'1-基础参数'!$C$25*'1-基础参数'!$C$22)*(1-'1-基础参数'!$C$26)-'2-单车成本测算'!$G$21-'2-单车成本测算'!$G$28-'2-单车成本测算'!$G$24-'2-单车成本测算'!$G$32)*'1-基础参数'!$C$33 -> 12234.831 | I10: =(D10-D10*'1-基础参数'!$C$25*'1-基础参数'!$C$22)*'1-基础参数'!$C$26+('2-单车成本测算'!$G$21*'1-基础参数'!$C$27/'2-单车成本测算'!$E$15*'1-基础参数'!$C$28+'2-单车成本测算'!$G$28*'1-基础参数'!$C$29)*'1-基础参数'!$C$34 -> 692.08687 | J10: =D10*'1-基础参数'!$C$25*'1-基础参数'!$C$22+G10+H10+I10+'2-单车成本测算'!$G$21*'1-基础参数'!$C$27/'2-单车成本测算'!$E$15*(1-'1-基础参数'!$C$28)+('2-单车成本测算'!$G$21*'1-基础参数'!$C$27/'2-单车成本测算'!$E$15*'1-基础参数'!$C$28+'2-单车成本测算'!$G$28*'1-基础参数'!$C$29)*(1-'1-基础参数'!$C$34) -> 31727.522
B11: 0.1 | C11: ='1-基础参数'!$C$6*(1+B11) -> 231 | D11: =C11*'1-基础参数'!$C$9*'1-基础参数'!$C$12 -> 82790.4 | E11: =D11-'2-单车成本测算'!$G$35 -> 11284.402 | F11: =IF(D11=0,0,E11/D11) -> 0.13630085 | G11: =((D11-D11*'1-基础参数'!$C$25*'1-基础参数'!$C$22)*(1-'1-基础参数'!$C$26)-'2-单车成本测算'!$G$21-'2-单车成本测算'!$G$28-'2-单车成本测算'!$G$24-'2-单车成本测算'!$G$32)*(1-'1-基础参数'!$C$33) -> 13365.028 | H11: =((D11-D11*'1-基础参数'!$C$25*'1-基础参数'!$C$22)*(1-'1-基础参数'!$C$26)-'2-单车成本测算'!$G$21-'2-单车成本测算'!$G$28-'2-单车成本测算'!$G$24-'2-单车成本测算'!$G$32)*'1-基础参数'!$C$33 -> 16335.034 | I11: =(D11-D11*'1-基础参数'!$C$25*'1-基础参数'!$C$22)*'1-基础参数'!$C$26+('2-单车成本测算'!$G$21*'1-基础参数'!$C$27/'2-单车成本测算'!$E$15*'1-基础参数'!$C$28+'2-单车成本测算'!$G$28*'1-基础参数'!$C$29)*'1-基础参数'!$C$34 -> 729.54875 | J11: =D11*'1-基础参数'!$C$25*'1-基础参数'!$C$22+G11+H11+I11+'2-单车成本测算'!$G$21*'1-基础参数'!$C$27/'2-单车成本测算'!$E$15*(1-'1-基础参数'!$C$28)+('2-单车成本测算'!$G$21*'1-基础参数'!$C$27/'2-单车成本测算'!$E$15*'1-基础参数'!$C$28+'2-单车成本测算'!$G$28*'1-基础参数'!$C$29)*(1-'1-基础参数'!$C$34) -> 39253.922
B12: 0.2 | C12: ='1-基础参数'!$C$6*(1+B12) -> 252 | D12: =C12*'1-基础参数'!$C$9*'1-基础参数'!$C$12 -> 90316.8 | E12: =D12-'2-单车成本测算'!$G$35 -> 18810.802 | F12: =IF(D12=0,0,E12/D12) -> 0.20827578 | G12: =((D12-D12*'1-基础参数'!$C$25*'1-基础参数'!$C$22)*(1-'1-基础参数'!$C$26)-'2-单车成本测算'!$G$21-'2-单车成本测算'!$G$28-'2-单车成本测算'!$G$24-'2-单车成本测算'!$G$32)*(1-'1-基础参数'!$C$33) -> 16719.739 | H12: =((D12-D12*'1-基础参数'!$C$25*'1-基础参数'!$C$22)*(1-'1-基础参数'!$C$26)-'2-单车成本测算'!$G$21-'2-单车成本测算'!$G$28-'2-单车成本测算'!$G$24-'2-单车成本测算'!$G$32)*'1-基础参数'!$C$33 -> 20435.237 | I12: =(D12-D12*'1-基础参数'!$C$25*'1-基础参数'!$C$22)*'1-基础参数'!$C$26+('2-单车成本测算'!$G$21*'1-基础参数'!$C$27/'2-单车成本测算'!$E$15*'1-基础参数'!$C$28+'2-单车成本测算'!$G$28*'1-基础参数'!$C$29)*'1-基础参数'!$C$34 -> 767.01063 | J12: =D12*'1-基础参数'!$C$25*'1-基础参数'!$C$22+G12+H12+I12+'2-单车成本测算'!$G$21*'1-基础参数'!$C$27/'2-单车成本测算'!$E$15*(1-'1-基础参数'!$C$28)+('2-单车成本测算'!$G$21*'1-基础参数'!$C$27/'2-单车成本测算'!$E$15*'1-基础参数'!$C$28+'2-单车成本测算'!$G$28*'1-基础参数'!$C$29)*(1-'1-基础参数'!$C$34) -> 46780.322
B13: 0.3 | C13: ='1-基础参数'!$C$6*(1+B13) -> 273 | D13: =C13*'1-基础参数'!$C$9*'1-基础参数'!$C$12 -> 97843.2 | E13: =D13-'2-单车成本测算'!$G$35 -> 26337.202 | F13: =IF(D13=0,0,E13/D13) -> 0.26917765 | G13: =((D13-D13*'1-基础参数'!$C$25*'1-基础参数'!$C$22)*(1-'1-基础参数'!$C$26)-'2-单车成本测算'!$G$21-'2-单车成本测算'!$G$28-'2-单车成本测算'!$G$24-'2-单车成本测算'!$G$32)*(1-'1-基础参数'!$C$33) -> 20074.451 | H13: =((D13-D13*'1-基础参数'!$C$25*'1-基础参数'!$C$22)*(1-'1-基础参数'!$C$26)-'2-单车成本测算'!$G$21-'2-单车成本测算'!$G$28-'2-单车成本测算'!$G$24-'2-单车成本测算'!$G$32)*'1-基础参数'!$C$33 -> 24535.44 | I13: =(D13-D13*'1-基础参数'!$C$25*'1-基础参数'!$C$22)*'1-基础参数'!$C$26+('2-单车成本测算'!$G$21*'1-基础参数'!$C$27/'2-单车成本测算'!$E$15*'1-基础参数'!$C$28+'2-单车成本测算'!$G$28*'1-基础参数'!$C$29)*'1-基础参数'!$C$34 -> 804.47252 | J13: =D13*'1-基础参数'!$C$25*'1-基础参数'!$C$22+G13+H13+I13+'2-单车成本测算'!$G$21*'1-基础参数'!$C$27/'2-单车成本测算'!$E$15*(1-'1-基础参数'!$C$28)+('2-单车成本测算'!$G$21*'1-基础参数'!$C$27/'2-单车成本测算'!$E$15*'1-基础参数'!$C$28+'2-单车成本测算'!$G$28*'1-基础参数'!$C$29)*(1-'1-基础参数'!$C$34) -> 54306.722
B15: 二、月趟数敏感性分析
B16: 变动幅度 | C16: 月趟数 （趟/月） | D16: 月收入 （元） | E16: 毛利润 （元） | F16: 毛利率 | G16: 物流服务 公司净收益 | H16: 承运物流 企业净收益 | I16: 平台公司 净收益 | J16: 全参与方 净收益合计
B17: -0.3 | C17: ='1-基础参数'!$C$12*(1+B17) -> 7.84 | D17: ='1-基础参数'!$C$6*'1-基础参数'!$C$9*C17 -> 52684.8 | E17: =D17-('2-单车成本测算'!$G$9+'2-单车成本测算'!$G$14+'2-单车成本测算'!$G$20*C17+'2-单车成本测算'!$E$27*'1-基础参数'!$C$8*C17+'2-单车成本测算'!$G$24+'2-单车成本测算'!$G$32+ROUND('1-基础参数'!$C$6*'1-基础参数'!$C$9*C17*'1-基础参数'!$C$32,2)) -> -7397.8678 | F17: =IF(D17=0,0,E17/D17) -> -0.1404175 | G17: =((D17-D17*'1-基础参数'!$C$25*'1-基础参数'!$C$22)*(1-'1-基础参数'!$C$26)-'2-单车成本测算'!$G$20*C17*'1-基础参数'!$C$12/'1-基础参数'!$C$12-'2-单车成本测算'!$E$27*'1-基础参数'!$C$8*C17-'2-单车成本测算'!$G$24-'2-单车成本测算'!$G$32)*(1-'1-基础参数'!$C$33) -> 4172.2212 | H17: =((D17-D17*'1-基础参数'!$C$25*'1-基础参数'!$C$22)*(1-'1-基础参数'!$C$26)-'2-单车成本测算'!$G$20*C17*'1-基础参数'!$C$12/'1-基础参数'!$C$12-'2-单车成本测算'!$E$27*'1-基础参数'!$C$8*C17-'2-单车成本测算'!$G$24-'2-单车成本测算'!$G$32)*'1-基础参数'!$C$33 -> 5099.3815 | I17: =(D17-D17*'1-基础参数'!$C$25*'1-基础参数'!$C$22)*'1-基础参数'!$C$26+('2-单车成本测算'!$G$20*C17*'1-基础参数'!$C$12/'1-基础参数'!$C$12*'1-基础参数'!$C$27/'2-单车成本测算'!$E$15*'1-基础参数'!$C$28+'2-单车成本测算'!$E$27*'1-基础参数'!$C$8*C17*'1-基础参数'!$C$29)*'1-基础参数'!$C$34 -> 484.46081 | J17: =D17*'1-基础参数'!$C$25*'1-基础参数'!$C$22+G17+H17+I17+'2-单车成本测算'!$G$20*C17*'1-基础参数'!$C$12/'1-基础参数'!$C$12*'1-基础参数'!$C$27/'2-单车成本测算'!$E$15*(1-'1-基础参数'!$C$28)+('2-单车成本测算'!$G$20*C17*'1-基础参数'!$C$12/'1-基础参数'!$C$12*'1-基础参数'!$C$27/'2-单车成本测算'!$E$15*'1-基础参数'!$C$28+'2-单车成本测算'!$E$27*'1-基础参数'!$C$8*C17*'1-基础参数'!$C$29)*(1-'1-基础参数'!$C$34) -> 15909.265
B18: -0.2 | C18: ='1-基础参数'!$C$12*(1+B18) -> 8.96 | D18: ='1-基础参数'!$C$6*'1-基础参数'!$C$9*C18 -> 60211.2 | E18: =D18-('2-单车成本测算'!$G$9+'2-单车成本测算'!$G$14+'2-单车成本测算'!$G$20*C18+'2-单车成本测算'!$E$27*'1-基础参数'!$C$8*C18+'2-单车成本测算'!$G$24+'2-单车成本测算'!$G$32+ROUND('1-基础参数'!$C$6*'1-基础参数'!$C$9*C18*'1-基础参数'!$C$32,2)) -> -3679.2478 | F18: =IF(D18=0,0,E18/D18) -> -0.061105705 | G18: =((D18-D18*'1-基础参数'!$C$25*'1-基础参数'!$C$22)*(1-'1-基础参数'!$C$26)-'2-单车成本测算'!$G$20*C18*'1-基础参数'!$C$12/'1-基础参数'!$C$12-'2-单车成本测算'!$E$27*'1-基础参数'!$C$8*C18-'2-单车成本测算'!$G$24-'2-单车成本测算'!$G$32)*(1-'1-基础参数'!$C$33) -> 6118.2528 | H18: =((D18-D18*'1-基础参数'!$C$25*'1-基础参数'!$C$22)*(1-'1-基础参数'!$C$26)-'2-单车成本测算'!$G$20*C18*'1-基础参数'!$C$12/'1-基础参数'!$C$12-'2-单车成本测算'!$E$27*'1-基础参数'!$C$8*C18-'2-单车成本测算'!$G$24-'2-单车成本测算'!$G$32)*'1-基础参数'!$C$33 -> 7477.8645 | I18: =(D18-D18*'1-基础参数'!$C$25*'1-基础参数'!$C$22)*'1-基础参数'!$C$26+('2-单车成本测算'!$G$20*C18*'1-基础参数'!$C$12/'1-基础参数'!$C$12*'1-基础参数'!$C$27/'2-单车成本测算'!$E$15*'1-基础参数'!$C$28+'2-单车成本测算'!$E$27*'1-基础参数'!$C$8*C18*'1-基础参数'!$C$29)*'1-基础参数'!$C$34 -> 553.66949 | J18: =D18*'1-基础参数'!$C$25*'1-基础参数'!$C$22+G18+H18+I18+'2-单车成本测算'!$G$20*C18*'1-基础参数'!$C$12/'1-基础参数'!$C$12*'1-基础参数'!$C$27/'2-单车成本测算'!$E$15*(1-'1-基础参数'!$C$28)+('2-单车成本测算'!$G$20*C18*'1-基础参数'!$C$12/'1-基础参数'!$C$12*'1-基础参数'!$C$27/'2-单车成本测算'!$E$15*'1-基础参数'!$C$28+'2-单车成本测算'!$E$27*'1-基础参数'!$C$8*C18*'1-基础参数'!$C$29)*(1-'1-基础参数'!$C$34) -> 21182.017
B19: -0.1 | C19: ='1-基础参数'!$C$12*(1+B19) -> 10.08 | D19: ='1-基础参数'!$C$6*'1-基础参数'!$C$9*C19 -> 67737.6 | E19: =D19-('2-单车成本测算'!$G$9+'2-单车成本测算'!$G$14+'2-单车成本测算'!$G$20*C19+'2-单车成本测算'!$E$27*'1-基础参数'!$C$8*C19+'2-单车成本测算'!$G$24+'2-单车成本测算'!$G$32+ROUND('1-基础参数'!$C$6*'1-基础参数'!$C$9*C19*'1-基础参数'!$C$32,2)) -> 39.382183 | F19: =IF(D19=0,0,E19/D19) -> 0.00058139325 | G19: =((D19-D19*'1-基础参数'!$C$25*'1-基础参数'!$C$22)*(1-'1-基础参数'!$C$26)-'2-单车成本测算'!$G$20*C19*'1-基础参数'!$C$12/'1-基础参数'!$C$12-'2-单车成本测算'!$E$27*'1-基础参数'!$C$8*C19-'2-单车成本测算'!$G$24-'2-单车成本测算'!$G$32)*(1-'1-基础参数'!$C$33) -> 8064.2844 | H19: =((D19-D19*'1-基础参数'!$C$25*'1-基础参数'!$C$22)*(1-'1-基础参数'!$C$26)-'2-单车成本测算'!$G$20*C19*'1-基础参数'!$C$12/'1-基础参数'!$C$12-'2-单车成本测算'!$E$27*'1-基础参数'!$C$8*C19-'2-单车成本测算'!$G$24-'2-单车成本测算'!$G$32)*'1-基础参数'!$C$33 -> 9856.3476 | I19: =(D19-D19*'1-基础参数'!$C$25*'1-基础参数'!$C$22)*'1-基础参数'!$C$26+('2-单车成本测算'!$G$20*C19*'1-基础参数'!$C$12/'1-基础参数'!$C$12*'1-基础参数'!$C$27/'2-单车成本测算'!$E$15*'1-基础参数'!$C$28+'2-单车成本测算'!$E$27*'1-基础参数'!$C$8*C19*'1-基础参数'!$C$29)*'1-基础参数'!$C$34 -> 622.87818 | J19: =D19*'1-基础参数'!$C$25*'1-基础参数'!$C$22+G19+H19+I19+'2-单车成本测算'!$G$20*C19*'1-基础参数'!$C$12/'1-基础参数'!$C$12*'1-基础参数'!$C$27/'2-单车成本测算'!$E$15*(1-'1-基础参数'!$C$28)+('2-单车成本测算'!$G$20*C19*'1-基础参数'!$C$12/'1-基础参数'!$C$12*'1-基础参数'!$C$27/'2-单车成本测算'!$E$15*'1-基础参数'!$C$28+'2-单车成本测算'!$E$27*'1-基础参数'!$C$8*C19*'1-基础参数'!$C$29)*(1-'1-基础参数'!$C$34) -> 26454.769
B20: 0 | C20: ='1-基础参数'!$C$12*(1+B20) -> 11.2 | D20: ='1-基础参数'!$C$6*'1-基础参数'!$C$9*C20 -> 75264 | E20: =D20-('2-单车成本测算'!$G$9+'2-单车成本测算'!$G$14+'2-单车成本测算'!$G$20*C20+'2-单车成本测算'!$E$27*'1-基础参数'!$C$8*C20+'2-单车成本测算'!$G$24+'2-单车成本测算'!$G$32+ROUND('1-基础参数'!$C$6*'1-基础参数'!$C$9*C20*'1-基础参数'!$C$32,2)) -> 3758.0022 | F20: =IF(D20=0,0,E20/D20) -> 0.049930939 | G20: =((D20-D20*'1-基础参数'!$C$25*'1-基础参数'!$C$22)*(1-'1-基础参数'!$C$26)-'2-单车成本测算'!$G$20*C20*'1-基础参数'!$C$12/'1-基础参数'!$C$12-'2-单车成本测算'!$E$27*'1-基础参数'!$C$8*C20-'2-单车成本测算'!$G$24-'2-单车成本测算'!$G$32)*(1-'1-基础参数'!$C$33) -> 10010.316 | H20: =((D20-D20*'1-基础参数'!$C$25*'1-基础参数'!$C$22)*(1-'1-基础参数'!$C$26)-'2-单车成本测算'!$G$20*C20*'1-基础参数'!$C$12/'1-基础参数'!$C$12-'2-单车成本测算'!$E$27*'1-基础参数'!$C$8*C20-'2-单车成本测算'!$G$24-'2-单车成本测算'!$G$32)*'1-基础参数'!$C$33 -> 12234.831 | I20: =(D20-D20*'1-基础参数'!$C$25*'1-基础参数'!$C$22)*'1-基础参数'!$C$26+('2-单车成本测算'!$G$20*C20*'1-基础参数'!$C$12/'1-基础参数'!$C$12*'1-基础参数'!$C$27/'2-单车成本测算'!$E$15*'1-基础参数'!$C$28+'2-单车成本测算'!$E$27*'1-基础参数'!$C$8*C20*'1-基础参数'!$C$29)*'1-基础参数'!$C$34 -> 692.08687 | J20: =D20*'1-基础参数'!$C$25*'1-基础参数'!$C$22+G20+H20+I20+'2-单车成本测算'!$G$20*C20*'1-基础参数'!$C$12/'1-基础参数'!$C$12*'1-基础参数'!$C$27/'2-单车成本测算'!$E$15*(1-'1-基础参数'!$C$28)+('2-单车成本测算'!$G$20*C20*'1-基础参数'!$C$12/'1-基础参数'!$C$12*'1-基础参数'!$C$27/'2-单车成本测算'!$E$15*'1-基础参数'!$C$28+'2-单车成本测算'!$E$27*'1-基础参数'!$C$8*C20*'1-基础参数'!$C$29)*(1-'1-基础参数'!$C$34) -> 31727.522
B21: 0.1 | C21: ='1-基础参数'!$C$12*(1+B21) -> 12.32 | D21: ='1-基础参数'!$C$6*'1-基础参数'!$C$9*C21 -> 82790.4 | E21: =D21-('2-单车成本测算'!$G$9+'2-单车成本测算'!$G$14+'2-单车成本测算'!$G$20*C21+'2-单车成本测算'!$E$27*'1-基础参数'!$C$8*C21+'2-单车成本测算'!$G$24+'2-单车成本测算'!$G$32+ROUND('1-基础参数'!$C$6*'1-基础参数'!$C$9*C21*'1-基础参数'!$C$32,2)) -> 7476.6222 | F21: =IF(D21=0,0,E21/D21) -> 0.09030784 | G21: =((D21-D21*'1-基础参数'!$C$25*'1-基础参数'!$C$22)*(1-'1-基础参数'!$C$26)-'2-单车成本测算'!$G$20*C21*'1-基础参数'!$C$12/'1-基础参数'!$C$12-'2-单车成本测算'!$E$27*'1-基础参数'!$C$8*C21-'2-单车成本测算'!$G$24-'2-单车成本测算'!$G$32)*(1-'1-基础参数'!$C$33) -> 11956.348 | H21: =((D21-D21*'1-基础参数'!$C$25*'1-基础参数'!$C$22)*(1-'1-基础参数'!$C$26)-'2-单车成本测算'!$G$20*C21*'1-基础参数'!$C$12/'1-基础参数'!$C$12-'2-单车成本测算'!$E$27*'1-基础参数'!$C$8*C21-'2-单车成本测算'!$G$24-'2-单车成本测算'!$G$32)*'1-基础参数'!$C$33 -> 14613.314 | I21: =(D21-D21*'1-基础参数'!$C$25*'1-基础参数'!$C$22)*'1-基础参数'!$C$26+('2-单车成本测算'!$G$20*C21*'1-基础参数'!$C$12/'1-基础参数'!$C$12*'1-基础参数'!$C$27/'2-单车成本测算'!$E$15*'1-基础参数'!$C$28+'2-单车成本测算'!$E$27*'1-基础参数'!$C$8*C21*'1-基础参数'!$C$29)*'1-基础参数'!$C$34 -> 761.29556 | J21: =D21*'1-基础参数'!$C$25*'1-基础参数'!$C$22+G21+H21+I21+'2-单车成本测算'!$G$20*C21*'1-基础参数'!$C$12/'1-基础参数'!$C$12*'1-基础参数'!$C$27/'2-单车成本测算'!$E$15*(1-'1-基础参数'!$C$28)+('2-单车成本测算'!$G$20*C21*'1-基础参数'!$C$12/'1-基础参数'!$C$12*'1-基础参数'!$C$27/'2-单车成本测算'!$E$15*'1-基础参数'!$C$28+'2-单车成本测算'!$E$27*'1-基础参数'!$C$8*C21*'1-基础参数'!$C$29)*(1-'1-基础参数'!$C$34) -> 37000.274
B22: 0.2 | C22: ='1-基础参数'!$C$12*(1+B22) -> 13.44 | D22: ='1-基础参数'!$C$6*'1-基础参数'!$C$9*C22 -> 90316.8 | E22: =D22-('2-单车成本测算'!$G$9+'2-单车成本测算'!$G$14+'2-单车成本测算'!$G$20*C22+'2-单车成本测算'!$E$27*'1-基础参数'!$C$8*C22+'2-单车成本测算'!$G$24+'2-单车成本测算'!$G$32+ROUND('1-基础参数'!$C$6*'1-基础参数'!$C$9*C22*'1-基础参数'!$C$32,2)) -> 11195.252 | F22: =IF(D22=0,0,E22/D22) -> 0.12395537 | G22: =((D22-D22*'1-基础参数'!$C$25*'1-基础参数'!$C$22)*(1-'1-基础参数'!$C$26)-'2-单车成本测算'!$G$20*C22*'1-基础参数'!$C$12/'1-基础参数'!$C$12-'2-单车成本测算'!$E$27*'1-基础参数'!$C$8*C22-'2-单车成本测算'!$G$24-'2-单车成本测算'!$G$32)*(1-'1-基础参数'!$C$33) -> 13902.379 | H22: =((D22-D22*'1-基础参数'!$C$25*'1-基础参数'!$C$22)*(1-'1-基础参数'!$C$26)-'2-单车成本测算'!$G$20*C22*'1-基础参数'!$C$12/'1-基础参数'!$C$12-'2-单车成本测算'!$E$27*'1-基础参数'!$C$8*C22-'2-单车成本测算'!$G$24-'2-单车成本测算'!$G$32)*'1-基础参数'!$C$33 -> 16991.797 | I22: =(D22-D22*'1-基础参数'!$C$25*'1-基础参数'!$C$22)*'1-基础参数'!$C$26+('2-单车成本测算'!$G$20*C22*'1-基础参数'!$C$12/'1-基础参数'!$C$12*'1-基础参数'!$C$27/'2-单车成本测算'!$E$15*'1-基础参数'!$C$28+'2-单车成本测算'!$E$27*'1-基础参数'!$C$8*C22*'1-基础参数'!$C$29)*'1-基础参数'!$C$34 -> 830.50424 | J22: =D22*'1-基础参数'!$C$25*'1-基础参数'!$C$22+G22+H22+I22+'2-单车成本测算'!$G$20*C22*'1-基础参数'!$C$12/'1-基础参数'!$C$12*'1-基础参数'!$C$27/'2-单车成本测算'!$E$15*(1-'1-基础参数'!$C$28)+('2-单车成本测算'!$G$20*C22*'1-基础参数'!$C$12/'1-基础参数'!$C$12*'1-基础参数'!$C$27/'2-单车成本测算'!$E$15*'1-基础参数'!$C$28+'2-单车成本测算'!$E$27*'1-基础参数'!$C$8*C22*'1-基础参数'!$C$29)*(1-'1-基础参数'!$C$34) -> 42273.026
B23: 0.3 | C23: ='1-基础参数'!$C$12*(1+B23) -> 14.56 | D23: ='1-基础参数'!$C$6*'1-基础参数'!$C$9*C23 -> 97843.2 | E23: =D23-('2-单车成本测算'!$G$9+'2-单车成本测算'!$G$14+'2-单车成本测算'!$G$20*C23+'2-单车成本测算'!$E$27*'1-基础参数'!$C$8*C23+'2-单车成本测算'!$G$24+'2-单车成本测算'!$G$32+ROUND('1-基础参数'!$C$6*'1-基础参数'!$C$9*C23*'1-基础参数'!$C$32,2)) -> 14913.872 | F23: =IF(D23=0,0,E23/D23) -> 0.15242625 | G23: =((D23-D23*'1-基础参数'!$C$25*'1-基础参数'!$C$22)*(1-'1-基础参数'!$C$26)-'2-单车成本测算'!$G$20*C23*'1-基础参数'!$C$12/'1-基础参数'!$C$12-'2-单车成本测算'!$E$27*'1-基础参数'!$C$8*C23-'2-单车成本测算'!$G$24-'2-单车成本测算'!$G$32)*(1-'1-基础参数'!$C$33) -> 15848.411 | H23: =((D23-D23*'1-基础参数'!$C$25*'1-基础参数'!$C$22)*(1-'1-基础参数'!$C$26)-'2-单车成本测算'!$G$20*C23*'1-基础参数'!$C$12/'1-基础参数'!$C$12-'2-单车成本测算'!$E$27*'1-基础参数'!$C$8*C23-'2-单车成本测算'!$G$24-'2-单车成本测算'!$G$32)*'1-基础参数'!$C$33 -> 19370.28 | I23: =(D23-D23*'1-基础参数'!$C$25*'1-基础参数'!$C$22)*'1-基础参数'!$C$26+('2-单车成本测算'!$G$20*C23*'1-基础参数'!$C$12/'1-基础参数'!$C$12*'1-基础参数'!$C$27/'2-单车成本测算'!$E$15*'1-基础参数'!$C$28+'2-单车成本测算'!$E$27*'1-基础参数'!$C$8*C23*'1-基础参数'!$C$29)*'1-基础参数'!$C$34 -> 899.71293 | J23: =D23*'1-基础参数'!$C$25*'1-基础参数'!$C$22+G23+H23+I23+'2-单车成本测算'!$G$20*C23*'1-基础参数'!$C$12/'1-基础参数'!$C$12*'1-基础参数'!$C$27/'2-单车成本测算'!$E$15*(1-'1-基础参数'!$C$28)+('2-单车成本测算'!$G$20*C23*'1-基础参数'!$C$12/'1-基础参数'!$C$12*'1-基础参数'!$C$27/'2-单车成本测算'!$E$15*'1-基础参数'!$C$28+'2-单车成本测算'!$E$27*'1-基础参数'!$C$8*C23*'1-基础参数'!$C$29)*(1-'1-基础参数'!$C$34) -> 47545.778
B25: 三、双参数交叉矩阵：运价 × 承运方分账比例 → 物流服务公司净收益（元/月）
B26: 运价 ↓ / 分账比例 → | C26: 0.4 | D26: 0.45 | E26: 0.5 | F26: 0.55 | G26: 0.6 | H26: 0.65 | I26: 0.7
B27: 147 | C27: =(($B27*'1-基础参数'!$C$9*'1-基础参数'!$C$12-$B27*'1-基础参数'!$C$9*'1-基础参数'!$C$12*'1-基础参数'!$C$25*'1-基础参数'!$C$22)*(1-'1-基础参数'!$C$26)-'2-单车成本测算'!$G$21-'2-单车成本测算'!$G$28-'2-单车成本测算'!$G$24-'2-单车成本测算'!$G$32)*(1-C$26) -> -71.758406 | D27: =(($B27*'1-基础参数'!$C$9*'1-基础参数'!$C$12-$B27*'1-基础参数'!$C$9*'1-基础参数'!$C$12*'1-基础参数'!$C$25*'1-基础参数'!$C$22)*(1-'1-基础参数'!$C$26)-'2-单车成本测算'!$G$21-'2-单车成本测算'!$G$28-'2-单车成本测算'!$G$24-'2-单车成本测算'!$G$32)*(1-D$26) -> -65.778539 | E27: =(($B27*'1-基础参数'!$C$9*'1-基础参数'!$C$12-$B27*'1-基础参数'!$C$9*'1-基础参数'!$C$12*'1-基础参数'!$C$25*'1-基础参数'!$C$22)*(1-'1-基础参数'!$C$26)-'2-单车成本测算'!$G$21-'2-单车成本测算'!$G$28-'2-单车成本测算'!$G$24-'2-单车成本测算'!$G$32)*(1-E$26) -> -59.798672 | F27: =(($B27*'1-基础参数'!$C$9*'1-基础参数'!$C$12-$B27*'1-基础参数'!$C$9*'1-基础参数'!$C$12*'1-基础参数'!$C$25*'1-基础参数'!$C$22)*(1-'1-基础参数'!$C$26)-'2-单车成本测算'!$G$21-'2-单车成本测算'!$G$28-'2-单车成本测算'!$G$24-'2-单车成本测算'!$G$32)*(1-F$26) -> -53.818805 | G27: =(($B27*'1-基础参数'!$C$9*'1-基础参数'!$C$12-$B27*'1-基础参数'!$C$9*'1-基础参数'!$C$12*'1-基础参数'!$C$25*'1-基础参数'!$C$22)*(1-'1-基础参数'!$C$26)-'2-单车成本测算'!$G$21-'2-单车成本测算'!$G$28-'2-单车成本测算'!$G$24-'2-单车成本测算'!$G$32)*(1-G$26) -> -47.838937 | H27: =(($B27*'1-基础参数'!$C$9*'1-基础参数'!$C$12-$B27*'1-基础参数'!$C$9*'1-基础参数'!$C$12*'1-基础参数'!$C$25*'1-基础参数'!$C$22)*(1-'1-基础参数'!$C$26)-'2-单车成本测算'!$G$21-'2-单车成本测算'!$G$28-'2-单车成本测算'!$G$24-'2-单车成本测算'!$G$32)*(1-H$26) -> -41.85907 | I27: =(($B27*'1-基础参数'!$C$9*'1-基础参数'!$C$12-$B27*'1-基础参数'!$C$9*'1-基础参数'!$C$12*'1-基础参数'!$C$25*'1-基础参数'!$C$22)*(1-'1-基础参数'!$C$26)-'2-单车成本测算'!$G$21-'2-单车成本测算'!$G$28-'2-单车成本测算'!$G$24-'2-单车成本测算'!$G$32)*(1-I$26) -> -35.879203
B28: 168 | C28: =(($B28*'1-基础参数'!$C$9*'1-基础参数'!$C$12-$B28*'1-基础参数'!$C$9*'1-基础参数'!$C$12*'1-基础参数'!$C$25*'1-基础参数'!$C$22)*(1-'1-基础参数'!$C$26)-'2-单车成本测算'!$G$21-'2-单车成本测算'!$G$28-'2-单车成本测算'!$G$24-'2-单车成本测算'!$G$32)*(1-C$26) -> 4401.1904 | D28: =(($B28*'1-基础参数'!$C$9*'1-基础参数'!$C$12-$B28*'1-基础参数'!$C$9*'1-基础参数'!$C$12*'1-基础参数'!$C$25*'1-基础参数'!$C$22)*(1-'1-基础参数'!$C$26)-'2-单车成本测算'!$G$21-'2-单车成本测算'!$G$28-'2-单车成本测算'!$G$24-'2-单车成本测算'!$G$32)*(1-D$26) -> 4034.4245 | E28: =(($B28*'1-基础参数'!$C$9*'1-基础参数'!$C$12-$B28*'1-基础参数'!$C$9*'1-基础参数'!$C$12*'1-基础参数'!$C$25*'1-基础参数'!$C$22)*(1-'1-基础参数'!$C$26)-'2-单车成本测算'!$G$21-'2-单车成本测算'!$G$28-'2-单车成本测算'!$G$24-'2-单车成本测算'!$G$32)*(1-E$26) -> 3667.6587 | F28: =(($B28*'1-基础参数'!$C$9*'1-基础参数'!$C$12-$B28*'1-基础参数'!$C$9*'1-基础参数'!$C$12*'1-基础参数'!$C$25*'1-基础参数'!$C$22)*(1-'1-基础参数'!$C$26)-'2-单车成本测算'!$G$21-'2-单车成本测算'!$G$28-'2-单车成本测算'!$G$24-'2-单车成本测算'!$G$32)*(1-F$26) -> 3300.8928 | G28: =(($B28*'1-基础参数'!$C$9*'1-基础参数'!$C$12-$B28*'1-基础参数'!$C$9*'1-基础参数'!$C$12*'1-基础参数'!$C$25*'1-基础参数'!$C$22)*(1-'1-基础参数'!$C$26)-'2-单车成本测算'!$G$21-'2-单车成本测算'!$G$28-'2-单车成本测算'!$G$24-'2-单车成本测算'!$G$32)*(1-G$26) -> 2934.1269 | H28: =(($B28*'1-基础参数'!$C$9*'1-基础参数'!$C$12-$B28*'1-基础参数'!$C$9*'1-基础参数'!$C$12*'1-基础参数'!$C$25*'1-基础参数'!$C$22)*(1-'1-基础参数'!$C$26)-'2-单车成本测算'!$G$21-'2-单车成本测算'!$G$28-'2-单车成本测算'!$G$24-'2-单车成本测算'!$G$32)*(1-H$26) -> 2567.3611 | I28: =(($B28*'1-基础参数'!$C$9*'1-基础参数'!$C$12-$B28*'1-基础参数'!$C$9*'1-基础参数'!$C$12*'1-基础参数'!$C$25*'1-基础参数'!$C$22)*(1-'1-基础参数'!$C$26)-'2-单车成本测算'!$G$21-'2-单车成本测算'!$G$28-'2-单车成本测算'!$G$24-'2-单车成本测算'!$G$32)*(1-I$26) -> 2200.5952
B29: 189 | C29: =(($B29*'1-基础参数'!$C$9*'1-基础参数'!$C$12-$B29*'1-基础参数'!$C$9*'1-基础参数'!$C$12*'1-基础参数'!$C$25*'1-基础参数'!$C$22)*(1-'1-基础参数'!$C$26)-'2-单车成本测算'!$G$21-'2-单车成本测算'!$G$28-'2-单车成本测算'!$G$24-'2-单车成本测算'!$G$32)*(1-C$26) -> 8874.1392 | D29: =(($B29*'1-基础参数'!$C$9*'1-基础参数'!$C$12-$B29*'1-基础参数'!$C$9*'1-基础参数'!$C$12*'1-基础参数'!$C$25*'1-基础参数'!$C$22)*(1-'1-基础参数'!$C$26)-'2-单车成本测算'!$G$21-'2-单车成本测算'!$G$28-'2-单车成本测算'!$G$24-'2-单车成本测算'!$G$32)*(1-D$26) -> 8134.6276 | E29: =(($B29*'1-基础参数'!$C$9*'1-基础参数'!$C$12-$B29*'1-基础参数'!$C$9*'1-基础参数'!$C$12*'1-基础参数'!$C$25*'1-基础参数'!$C$22)*(1-'1-基础参数'!$C$26)-'2-单车成本测算'!$G$21-'2-单车成本测算'!$G$28-'2-单车成本测算'!$G$24-'2-单车成本测算'!$G$32)*(1-E$26) -> 7395.116 | F29: =(($B29*'1-基础参数'!$C$9*'1-基础参数'!$C$12-$B29*'1-基础参数'!$C$9*'1-基础参数'!$C$12*'1-基础参数'!$C$25*'1-基础参数'!$C$22)*(1-'1-基础参数'!$C$26)-'2-单车成本测算'!$G$21-'2-单车成本测算'!$G$28-'2-单车成本测算'!$G$24-'2-单车成本测算'!$G$32)*(1-F$26) -> 6655.6044 | G29: =(($B29*'1-基础参数'!$C$9*'1-基础参数'!$C$12-$B29*'1-基础参数'!$C$9*'1-基础参数'!$C$12*'1-基础参数'!$C$25*'1-基础参数'!$C$22)*(1-'1-基础参数'!$C$26)-'2-单车成本测算'!$G$21-'2-单车成本测算'!$G$28-'2-单车成本测算'!$G$24-'2-单车成本测算'!$G$32)*(1-G$26) -> 5916.0928 | H29: =(($B29*'1-基础参数'!$C$9*'1-基础参数'!$C$12-$B29*'1-基础参数'!$C$9*'1-基础参数'!$C$12*'1-基础参数'!$C$25*'1-基础参数'!$C$22)*(1-'1-基础参数'!$C$26)-'2-单车成本测算'!$G$21-'2-单车成本测算'!$G$28-'2-单车成本测算'!$G$24-'2-单车成本测算'!$G$32)*(1-H$26) -> 5176.5812 | I29: =(($B29*'1-基础参数'!$C$9*'1-基础参数'!$C$12-$B29*'1-基础参数'!$C$9*'1-基础参数'!$C$12*'1-基础参数'!$C$25*'1-基础参数'!$C$22)*(1-'1-基础参数'!$C$26)-'2-单车成本测算'!$G$21-'2-单车成本测算'!$G$28-'2-单车成本测算'!$G$24-'2-单车成本测算'!$G$32)*(1-I$26) -> 4437.0696
B30: 210 | C30: =(($B30*'1-基础参数'!$C$9*'1-基础参数'!$C$12-$B30*'1-基础参数'!$C$9*'1-基础参数'!$C$12*'1-基础参数'!$C$25*'1-基础参数'!$C$22)*(1-'1-基础参数'!$C$26)-'2-单车成本测算'!$G$21-'2-单车成本测算'!$G$28-'2-单车成本测算'!$G$24-'2-单车成本测算'!$G$32)*(1-C$26) -> 13347.088 | D30: =(($B30*'1-基础参数'!$C$9*'1-基础参数'!$C$12-$B30*'1-基础参数'!$C$9*'1-基础参数'!$C$12*'1-基础参数'!$C$25*'1-基础参数'!$C$22)*(1-'1-基础参数'!$C$26)-'2-单车成本测算'!$G$21-'2-单车成本测算'!$G$28-'2-单车成本测算'!$G$24-'2-单车成本测算'!$G$32)*(1-D$26) -> 12234.831 | E30: =(($B30*'1-基础参数'!$C$9*'1-基础参数'!$C$12-$B30*'1-基础参数'!$C$9*'1-基础参数'!$C$12*'1-基础参数'!$C$25*'1-基础参数'!$C$22)*(1-'1-基础参数'!$C$26)-'2-单车成本测算'!$G$21-'2-单车成本测算'!$G$28-'2-单车成本测算'!$G$24-'2-单车成本测算'!$G$32)*(1-E$26) -> 11122.573 | F30: =(($B30*'1-基础参数'!$C$9*'1-基础参数'!$C$12-$B30*'1-基础参数'!$C$9*'1-基础参数'!$C$12*'1-基础参数'!$C$25*'1-基础参数'!$C$22)*(1-'1-基础参数'!$C$26)-'2-单车成本测算'!$G$21-'2-单车成本测算'!$G$28-'2-单车成本测算'!$G$24-'2-单车成本测算'!$G$32)*(1-F$26) -> 10010.316 | G30: =(($B30*'1-基础参数'!$C$9*'1-基础参数'!$C$12-$B30*'1-基础参数'!$C$9*'1-基础参数'!$C$12*'1-基础参数'!$C$25*'1-基础参数'!$C$22)*(1-'1-基础参数'!$C$26)-'2-单车成本测算'!$G$21-'2-单车成本测算'!$G$28-'2-单车成本测算'!$G$24-'2-单车成本测算'!$G$32)*(1-G$26) -> 8898.0587 | H30: =(($B30*'1-基础参数'!$C$9*'1-基础参数'!$C$12-$B30*'1-基础参数'!$C$9*'1-基础参数'!$C$12*'1-基础参数'!$C$25*'1-基础参数'!$C$22)*(1-'1-基础参数'!$C$26)-'2-单车成本测算'!$G$21-'2-单车成本测算'!$G$28-'2-单车成本测算'!$G$24-'2-单车成本测算'!$G$32)*(1-H$26) -> 7785.8013 | I30: =(($B30*'1-基础参数'!$C$9*'1-基础参数'!$C$12-$B30*'1-基础参数'!$C$9*'1-基础参数'!$C$12*'1-基础参数'!$C$25*'1-基础参数'!$C$22)*(1-'1-基础参数'!$C$26)-'2-单车成本测算'!$G$21-'2-单车成本测算'!$G$28-'2-单车成本测算'!$G$24-'2-单车成本测算'!$G$32)*(1-I$26) -> 6673.544
B31: 231 | C31: =(($B31*'1-基础参数'!$C$9*'1-基础参数'!$C$12-$B31*'1-基础参数'!$C$9*'1-基础参数'!$C$12*'1-基础参数'!$C$25*'1-基础参数'!$C$22)*(1-'1-基础参数'!$C$26)-'2-单车成本测算'!$G$21-'2-单车成本测算'!$G$28-'2-单车成本测算'!$G$24-'2-单车成本测算'!$G$32)*(1-C$26) -> 17820.037 | D31: =(($B31*'1-基础参数'!$C$9*'1-基础参数'!$C$12-$B31*'1-基础参数'!$C$9*'1-基础参数'!$C$12*'1-基础参数'!$C$25*'1-基础参数'!$C$22)*(1-'1-基础参数'!$C$26)-'2-单车成本测算'!$G$21-'2-单车成本测算'!$G$28-'2-单车成本测算'!$G$24-'2-单车成本测算'!$G$32)*(1-D$26) -> 16335.034 | E31: =(($B31*'1-基础参数'!$C$9*'1-基础参数'!$C$12-$B31*'1-基础参数'!$C$9*'1-基础参数'!$C$12*'1-基础参数'!$C$25*'1-基础参数'!$C$22)*(1-'1-基础参数'!$C$26)-'2-单车成本测算'!$G$21-'2-单车成本测算'!$G$28-'2-单车成本测算'!$G$24-'2-单车成本测算'!$G$32)*(1-E$26) -> 14850.031 | F31: =(($B31*'1-基础参数'!$C$9*'1-基础参数'!$C$12-$B31*'1-基础参数'!$C$9*'1-基础参数'!$C$12*'1-基础参数'!$C$25*'1-基础参数'!$C$22)*(1-'1-基础参数'!$C$26)-'2-单车成本测算'!$G$21-'2-单车成本测算'!$G$28-'2-单车成本测算'!$G$24-'2-单车成本测算'!$G$32)*(1-F$26) -> 13365.028 | G31: =(($B31*'1-基础参数'!$C$9*'1-基础参数'!$C$12-$B31*'1-基础参数'!$C$9*'1-基础参数'!$C$12*'1-基础参数'!$C$25*'1-基础参数'!$C$22)*(1-'1-基础参数'!$C$26)-'2-单车成本测算'!$G$21-'2-单车成本测算'!$G$28-'2-单车成本测算'!$G$24-'2-单车成本测算'!$G$32)*(1-G$26) -> 11880.025 | H31: =(($B31*'1-基础参数'!$C$9*'1-基础参数'!$C$12-$B31*'1-基础参数'!$C$9*'1-基础参数'!$C$12*'1-基础参数'!$C$25*'1-基础参数'!$C$22)*(1-'1-基础参数'!$C$26)-'2-单车成本测算'!$G$21-'2-单车成本测算'!$G$28-'2-单车成本测算'!$G$24-'2-单车成本测算'!$G$32)*(1-H$26) -> 10395.021 | I31: =(($B31*'1-基础参数'!$C$9*'1-基础参数'!$C$12-$B31*'1-基础参数'!$C$9*'1-基础参数'!$C$12*'1-基础参数'!$C$25*'1-基础参数'!$C$22)*(1-'1-基础参数'!$C$26)-'2-单车成本测算'!$G$21-'2-单车成本测算'!$G$28-'2-单车成本测算'!$G$24-'2-单车成本测算'!$G$32)*(1-I$26) -> 8910.0184
B32: 252 | C32: =(($B32*'1-基础参数'!$C$9*'1-基础参数'!$C$12-$B32*'1-基础参数'!$C$9*'1-基础参数'!$C$12*'1-基础参数'!$C$25*'1-基础参数'!$C$22)*(1-'1-基础参数'!$C$26)-'2-单车成本测算'!$G$21-'2-单车成本测算'!$G$28-'2-单车成本测算'!$G$24-'2-单车成本测算'!$G$32)*(1-C$26) -> 22292.986 | D32: =(($B32*'1-基础参数'!$C$9*'1-基础参数'!$C$12-$B32*'1-基础参数'!$C$9*'1-基础参数'!$C$12*'1-基础参数'!$C$25*'1-基础参数'!$C$22)*(1-'1-基础参数'!$C$26)-'2-单车成本测算'!$G$21-'2-单车成本测算'!$G$28-'2-单车成本测算'!$G$24-'2-单车成本测算'!$G$32)*(1-D$26) -> 20435.237 | E32: =(($B32*'1-基础参数'!$C$9*'1-基础参数'!$C$12-$B32*'1-基础参数'!$C$9*'1-基础参数'!$C$12*'1-基础参数'!$C$25*'1-基础参数'!$C$22)*(1-'1-基础参数'!$C$26)-'2-单车成本测算'!$G$21-'2-单车成本测算'!$G$28-'2-单车成本测算'!$G$24-'2-单车成本测算'!$G$32)*(1-E$26) -> 18577.488 | F32: =(($B32*'1-基础参数'!$C$9*'1-基础参数'!$C$12-$B32*'1-基础参数'!$C$9*'1-基础参数'!$C$12*'1-基础参数'!$C$25*'1-基础参数'!$C$22)*(1-'1-基础参数'!$C$26)-'2-单车成本测算'!$G$21-'2-单车成本测算'!$G$28-'2-单车成本测算'!$G$24-'2-单车成本测算'!$G$32)*(1-F$26) -> 16719.739 | G32: =(($B32*'1-基础参数'!$C$9*'1-基础参数'!$C$12-$B32*'1-基础参数'!$C$9*'1-基础参数'!$C$12*'1-基础参数'!$C$25*'1-基础参数'!$C$22)*(1-'1-基础参数'!$C$26)-'2-单车成本测算'!$G$21-'2-单车成本测算'!$G$28-'2-单车成本测算'!$G$24-'2-单车成本测算'!$G$32)*(1-G$26) -> 14861.99 | H32: =(($B32*'1-基础参数'!$C$9*'1-基础参数'!$C$12-$B32*'1-基础参数'!$C$9*'1-基础参数'!$C$12*'1-基础参数'!$C$25*'1-基础参数'!$C$22)*(1-'1-基础参数'!$C$26)-'2-单车成本测算'!$G$21-'2-单车成本测算'!$G$28-'2-单车成本测算'!$G$24-'2-单车成本测算'!$G$32)*(1-H$26) -> 13004.242 | I32: =(($B32*'1-基础参数'!$C$9*'1-基础参数'!$C$12-$B32*'1-基础参数'!$C$9*'1-基础参数'!$C$12*'1-基础参数'!$C$25*'1-基础参数'!$C$22)*(1-'1-基础参数'!$C$26)-'2-单车成本测算'!$G$21-'2-单车成本测算'!$G$28-'2-单车成本测算'!$G$24-'2-单车成本测算'!$G$32)*(1-I$26) -> 11146.493
B33: 273 | C33: =(($B33*'1-基础参数'!$C$9*'1-基础参数'!$C$12-$B33*'1-基础参数'!$C$9*'1-基础参数'!$C$12*'1-基础参数'!$C$25*'1-基础参数'!$C$22)*(1-'1-基础参数'!$C$26)-'2-单车成本测算'!$G$21-'2-单车成本测算'!$G$28-'2-单车成本测算'!$G$24-'2-单车成本测算'!$G$32)*(1-C$26) -> 26765.934 | D33: =(($B33*'1-基础参数'!$C$9*'1-基础参数'!$C$12-$B33*'1-基础参数'!$C$9*'1-基础参数'!$C$12*'1-基础参数'!$C$25*'1-基础参数'!$C$22)*(1-'1-基础参数'!$C$26)-'2-单车成本测算'!$G$21-'2-单车成本测算'!$G$28-'2-单车成本测算'!$G$24-'2-单车成本测算'!$G$32)*(1-D$26) -> 24535.44 | E33: =(($B33*'1-基础参数'!$C$9*'1-基础参数'!$C$12-$B33*'1-基础参数'!$C$9*'1-基础参数'!$C$12*'1-基础参数'!$C$25*'1-基础参数'!$C$22)*(1-'1-基础参数'!$C$26)-'2-单车成本测算'!$G$21-'2-单车成本测算'!$G$28-'2-单车成本测算'!$G$24-'2-单车成本测算'!$G$32)*(1-E$26) -> 22304.945 | F33: =(($B33*'1-基础参数'!$C$9*'1-基础参数'!$C$12-$B33*'1-基础参数'!$C$9*'1-基础参数'!$C$12*'1-基础参数'!$C$25*'1-基础参数'!$C$22)*(1-'1-基础参数'!$C$26)-'2-单车成本测算'!$G$21-'2-单车成本测算'!$G$28-'2-单车成本测算'!$G$24-'2-单车成本测算'!$G$32)*(1-F$26) -> 20074.451 | G33: =(($B33*'1-基础参数'!$C$9*'1-基础参数'!$C$12-$B33*'1-基础参数'!$C$9*'1-基础参数'!$C$12*'1-基础参数'!$C$25*'1-基础参数'!$C$22)*(1-'1-基础参数'!$C$26)-'2-单车成本测算'!$G$21-'2-单车成本测算'!$G$28-'2-单车成本测算'!$G$24-'2-单车成本测算'!$G$32)*(1-G$26) -> 17843.956 | H33: =(($B33*'1-基础参数'!$C$9*'1-基础参数'!$C$12-$B33*'1-基础参数'!$C$9*'1-基础参数'!$C$12*'1-基础参数'!$C$25*'1-基础参数'!$C$22)*(1-'1-基础参数'!$C$26)-'2-单车成本测算'!$G$21-'2-单车成本测算'!$G$28-'2-单车成本测算'!$G$24-'2-单车成本测算'!$G$32)*(1-H$26) -> 15613.462 | I33: =(($B33*'1-基础参数'!$C$9*'1-基础参数'!$C$12-$B33*'1-基础参数'!$C$9*'1-基础参数'!$C$12*'1-基础参数'!$C$25*'1-基础参数'!$C$22)*(1-'1-基础参数'!$C$26)-'2-单车成本测算'!$G$21-'2-单车成本测算'!$G$28-'2-单车成本测算'!$G$24-'2-单车成本测算'!$G$32)*(1-I$26) -> 13382.967
B35: 四、运价变动 → 各参与方净收益对比（购置 vs 租赁，元/月）
B36: 运价 （元/吨） | C36: 合同物流 企业（购） | D36: 合同物流 企业（租） | E36: 物流服务 公司（购） | F36: 物流服务 公司（租） | G36: 承运方 （购） | H36: 承运方 （租） | I36: 全参与方 合计（购） | J36: 全参与方 合计（租）
B37: 147 | C37: =$B37*'1-基础参数'!$C$9*'1-基础参数'!$C$12*'1-基础参数'!$C$25*'1-基础参数'!$C$22 -> 238.16416 | D37: =$B37*'1-基础参数'!$C$9*'1-基础参数'!$C$12*'1-基础参数'!$C$25*'1-基础参数'!$C$22+'2-单车成本测算'!$H$10*'1-基础参数'!$C$25*'1-基础参数'!$C$23 -> 305.78403 | E37: =(($B37*'1-基础参数'!$C$9*'1-基础参数'!$C$12-$B37*'1-基础参数'!$C$9*'1-基础参数'!$C$12*'1-基础参数'!$C$25*'1-基础参数'!$C$22)*(1-'1-基础参数'!$C$26)-'2-单车成本测算'!$G$21-'2-单车成本测算'!$G$28-'2-单车成本测算'!$G$24-'2-单车成本测算'!$G$32)*(1-'1-基础参数'!$C$33) -> -53.818805 | F37: =(($B37*'1-基础参数'!$C$9*'1-基础参数'!$C$12-$B37*'1-基础参数'!$C$9*'1-基础参数'!$C$12*'1-基础参数'!$C$25*'1-基础参数'!$C$22-'2-单车成本测算'!$H$10)*(1-'1-基础参数'!$C$26)-'2-单车成本测算'!$G$21-'2-单车成本测算'!$G$28-'2-单车成本测算'!$G$24-'2-单车成本测算'!$G$32)*(1-'1-基础参数'!$C$33) -> -6751.4126 | G37: =(($B37*'1-基础参数'!$C$9*'1-基础参数'!$C$12-$B37*'1-基础参数'!$C$9*'1-基础参数'!$C$12*'1-基础参数'!$C$25*'1-基础参数'!$C$22)*(1-'1-基础参数'!$C$26)-'2-单车成本测算'!$G$21-'2-单车成本测算'!$G$28-'2-单车成本测算'!$G$24-'2-单车成本测算'!$G$32)*'1-基础参数'!$C$33 -> -65.778539 | H37: =(($B37*'1-基础参数'!$C$9*'1-基础参数'!$C$12-$B37*'1-基础参数'!$C$9*'1-基础参数'!$C$12*'1-基础参数'!$C$25*'1-基础参数'!$C$22-'2-单车成本测算'!$H$10)*(1-'1-基础参数'!$C$26)-'2-单车成本测算'!$G$21-'2-单车成本测算'!$G$28-'2-单车成本测算'!$G$24-'2-单车成本测算'!$G$32)*'1-基础参数'!$C$33 -> -8251.7265 | I37: =C37+E37+G37+($B37*'1-基础参数'!$C$9*'1-基础参数'!$C$12-$B37*'1-基础参数'!$C$9*'1-基础参数'!$C$12*'1-基础参数'!$C$25*'1-基础参数'!$C$22)*'1-基础参数'!$C$26+('2-单车成本测算'!$G$21*'1-基础参数'!$C$27/'2-单车成本测算'!$E$15*'1-基础参数'!$C$28+'2-单车成本测算'!$G$28*'1-基础参数'!$C$29)*'1-基础参数'!$C$34+'2-单车成本测算'!$G$21*'1-基础参数'!$C$27/'2-单车成本测算'!$E$15*(1-'1-基础参数'!$C$28)+('2-单车成本测算'!$G$21*'1-基础参数'!$C$27/'2-单车成本测算'!$E$15*'1-基础参数'!$C$28+'2-单车成本测算'!$G$28*'1-基础参数'!$C$29)*(1-'1-基础参数'!$C$34) -> 9148.3216 | J37: =D37+F37+H37+($B37*'1-基础参数'!$C$9*'1-基础参数'!$C$12-$B37*'1-基础参数'!$C$9*'1-基础参数'!$C$12*'1-基础参数'!$C$25*'1-基础参数'!$C$22-'2-单车成本测算'!$H$10)*'1-基础参数'!$C$26+200+('2-单车成本测算'!$G$21*'1-基础参数'!$C$27/'2-单车成本测算'!$E$15*'1-基础参数'!$C$28+'2-单车成本测算'!$G$28*'1-基础参数'!$C$29+'2-单车成本测算'!$G$14*'1-基础参数'!$C$30)*'1-基础参数'!$C$34+'2-单车成本测算'!$G$21*'1-基础参数'!$C$27/'2-单车成本测算'!$E$15*(1-'1-基础参数'!$C$28)+('2-单车成本测算'!$G$21*'1-基础参数'!$C$27/'2-单车成本测算'!$E$15*'1-基础参数'!$C$28+'2-单车成本测算'!$G$28*'1-基础参数'!$C$29+'2-单车成本测算'!$G$14*'1-基础参数'!$C$30)*(1-'1-基础参数'!$C$34)+'2-单车成本测算'!$G$9*0.15/1.15+'3.5-资金清分'!$E$55 -> -3081.001
B38: 168 | C38: =$B38*'1-基础参数'!$C$9*'1-基础参数'!$C$12*'1-基础参数'!$C$25*'1-基础参数'!$C$22 -> 272.18762 | D38: =$B38*'1-基础参数'!$C$9*'1-基础参数'!$C$12*'1-基础参数'!$C$25*'1-基础参数'!$C$22+'2-单车成本测算'!$H$10*'1-基础参数'!$C$25*'1-基础参数'!$C$23 -> 339.80748 | E38: =(($B38*'1-基础参数'!$C$9*'1-基础参数'!$C$12-$B38*'1-基础参数'!$C$9*'1-基础参数'!$C$12*'1-基础参数'!$C$25*'1-基础参数'!$C$22)*(1-'1-基础参数'!$C$26)-'2-单车成本测算'!$G$21-'2-单车成本测算'!$G$28-'2-单车成本测算'!$G$24-'2-单车成本测算'!$G$32)*(1-'1-基础参数'!$C$33) -> 3300.8928 | F38: =(($B38*'1-基础参数'!$C$9*'1-基础参数'!$C$12-$B38*'1-基础参数'!$C$9*'1-基础参数'!$C$12*'1-基础参数'!$C$25*'1-基础参数'!$C$22-'2-单车成本测算'!$H$10)*(1-'1-基础参数'!$C$26)-'2-单车成本测算'!$G$21-'2-单车成本测算'!$G$28-'2-单车成本测算'!$G$24-'2-单车成本测算'!$G$32)*(1-'1-基础参数'!$C$33) -> -3396.701 | G38: =(($B38*'1-基础参数'!$C$9*'1-基础参数'!$C$12-$B38*'1-基础参数'!$C$9*'1-基础参数'!$C$12*'1-基础参数'!$C$25*'1-基础参数'!$C$22)*(1-'1-基础参数'!$C$26)-'2-单车成本测算'!$G$21-'2-单车成本测算'!$G$28-'2-单车成本测算'!$G$24-'2-单车成本测算'!$G$32)*'1-基础参数'!$C$33 -> 4034.4245 | H38: =(($B38*'1-基础参数'!$C$9*'1-基础参数'!$C$12-$B38*'1-基础参数'!$C$9*'1-基础参数'!$C$12*'1-基础参数'!$C$25*'1-基础参数'!$C$22-'2-单车成本测算'!$H$10)*(1-'1-基础参数'!$C$26)-'2-单车成本测算'!$G$21-'2-单车成本测算'!$G$28-'2-单车成本测算'!$G$24-'2-单车成本测算'!$G$32)*'1-基础参数'!$C$33 -> -4151.5234 | I38: =C38+E38+G38+($B38*'1-基础参数'!$C$9*'1-基础参数'!$C$12-$B38*'1-基础参数'!$C$9*'1-基础参数'!$C$12*'1-基础参数'!$C$25*'1-基础参数'!$C$22)*'1-基础参数'!$C$26+('2-单车成本测算'!$G$21*'1-基础参数'!$C$27/'2-单车成本测算'!$E$15*'1-基础参数'!$C$28+'2-单车成本测算'!$G$28*'1-基础参数'!$C$29)*'1-基础参数'!$C$34+'2-单车成本测算'!$G$21*'1-基础参数'!$C$27/'2-单车成本测算'!$E$15*(1-'1-基础参数'!$C$28)+('2-单车成本测算'!$G$21*'1-基础参数'!$C$27/'2-单车成本测算'!$E$15*'1-基础参数'!$C$28+'2-单车成本测算'!$G$28*'1-基础参数'!$C$29)*(1-'1-基础参数'!$C$34) -> 16674.722 | J38: =D38+F38+H38+($B38*'1-基础参数'!$C$9*'1-基础参数'!$C$12-$B38*'1-基础参数'!$C$9*'1-基础参数'!$C$12*'1-基础参数'!$C$25*'1-基础参数'!$C$22-'2-单车成本测算'!$H$10)*'1-基础参数'!$C$26+200+('2-单车成本测算'!$G$21*'1-基础参数'!$C$27/'2-单车成本测算'!$E$15*'1-基础参数'!$C$28+'2-单车成本测算'!$G$28*'1-基础参数'!$C$29+'2-单车成本测算'!$G$14*'1-基础参数'!$C$30)*'1-基础参数'!$C$34+'2-单车成本测算'!$G$21*'1-基础参数'!$C$27/'2-单车成本测算'!$E$15*(1-'1-基础参数'!$C$28)+('2-单车成本测算'!$G$21*'1-基础参数'!$C$27/'2-单车成本测算'!$E$15*'1-基础参数'!$C$28+'2-单车成本测算'!$G$28*'1-基础参数'!$C$29+'2-单车成本测算'!$G$14*'1-基础参数'!$C$30)*(1-'1-基础参数'!$C$34)+'2-单车成本测算'!$G$9*0.15/1.15+'3.5-资金清分'!$E$55 -> 4445.399
B39: 189 | C39: =$B39*'1-基础参数'!$C$9*'1-基础参数'!$C$12*'1-基础参数'!$C$25*'1-基础参数'!$C$22 -> 306.21107 | D39: =$B39*'1-基础参数'!$C$9*'1-基础参数'!$C$12*'1-基础参数'!$C$25*'1-基础参数'!$C$22+'2-单车成本测算'!$H$10*'1-基础参数'!$C$25*'1-基础参数'!$C$23 -> 373.83093 | E39: =(($B39*'1-基础参数'!$C$9*'1-基础参数'!$C$12-$B39*'1-基础参数'!$C$9*'1-基础参数'!$C$12*'1-基础参数'!$C$25*'1-基础参数'!$C$22)*(1-'1-基础参数'!$C$26)-'2-单车成本测算'!$G$21-'2-单车成本测算'!$G$28-'2-单车成本测算'!$G$24-'2-单车成本测算'!$G$32)*(1-'1-基础参数'!$C$33) -> 6655.6044 | F39: =(($B39*'1-基础参数'!$C$9*'1-基础参数'!$C$12-$B39*'1-基础参数'!$C$9*'1-基础参数'!$C$12*'1-基础参数'!$C$25*'1-基础参数'!$C$22-'2-单车成本测算'!$H$10)*(1-'1-基础参数'!$C$26)-'2-单车成本测算'!$G$21-'2-单车成本测算'!$G$28-'2-单车成本测算'!$G$24-'2-单车成本测算'!$G$32)*(1-'1-基础参数'!$C$33) -> -41.989356 | G39: =(($B39*'1-基础参数'!$C$9*'1-基础参数'!$C$12-$B39*'1-基础参数'!$C$9*'1-基础参数'!$C$12*'1-基础参数'!$C$25*'1-基础参数'!$C$22)*(1-'1-基础参数'!$C$26)-'2-单车成本测算'!$G$21-'2-单车成本测算'!$G$28-'2-单车成本测算'!$G$24-'2-单车成本测算'!$G$32)*'1-基础参数'!$C$33 -> 8134.6276 | H39: =(($B39*'1-基础参数'!$C$9*'1-基础参数'!$C$12-$B39*'1-基础参数'!$C$9*'1-基础参数'!$C$12*'1-基础参数'!$C$25*'1-基础参数'!$C$22-'2-单车成本测算'!$H$10)*(1-'1-基础参数'!$C$26)-'2-单车成本测算'!$G$21-'2-单车成本测算'!$G$28-'2-单车成本测算'!$G$24-'2-单车成本测算'!$G$32)*'1-基础参数'!$C$33 -> -51.320324 | I39: =C39+E39+G39+($B39*'1-基础参数'!$C$9*'1-基础参数'!$C$12-$B39*'1-基础参数'!$C$9*'1-基础参数'!$C$12*'1-基础参数'!$C$25*'1-基础参数'!$C$22)*'1-基础参数'!$C$26+('2-单车成本测算'!$G$21*'1-基础参数'!$C$27/'2-单车成本测算'!$E$15*'1-基础参数'!$C$28+'2-单车成本测算'!$G$28*'1-基础参数'!$C$29)*'1-基础参数'!$C$34+'2-单车成本测算'!$G$21*'1-基础参数'!$C$27/'2-单车成本测算'!$E$15*(1-'1-基础参数'!$C$28)+('2-单车成本测算'!$G$21*'1-基础参数'!$C$27/'2-单车成本测算'!$E$15*'1-基础参数'!$C$28+'2-单车成本测算'!$G$28*'1-基础参数'!$C$29)*(1-'1-基础参数'!$C$34) -> 24201.122 | J39: =D39+F39+H39+($B39*'1-基础参数'!$C$9*'1-基础参数'!$C$12-$B39*'1-基础参数'!$C$9*'1-基础参数'!$C$12*'1-基础参数'!$C$25*'1-基础参数'!$C$22-'2-单车成本测算'!$H$10)*'1-基础参数'!$C$26+200+('2-单车成本测算'!$G$21*'1-基础参数'!$C$27/'2-单车成本测算'!$E$15*'1-基础参数'!$C$28+'2-单车成本测算'!$G$28*'1-基础参数'!$C$29+'2-单车成本测算'!$G$14*'1-基础参数'!$C$30)*'1-基础参数'!$C$34+'2-单车成本测算'!$G$21*'1-基础参数'!$C$27/'2-单车成本测算'!$E$15*(1-'1-基础参数'!$C$28)+('2-单车成本测算'!$G$21*'1-基础参数'!$C$27/'2-单车成本测算'!$E$15*'1-基础参数'!$C$28+'2-单车成本测算'!$G$28*'1-基础参数'!$C$29+'2-单车成本测算'!$G$14*'1-基础参数'!$C$30)*(1-'1-基础参数'!$C$34)+'2-单车成本测算'!$G$9*0.15/1.15+'3.5-资金清分'!$E$55 -> 11971.799
B40: 210 | C40: =$B40*'1-基础参数'!$C$9*'1-基础参数'!$C$12*'1-基础参数'!$C$25*'1-基础参数'!$C$22 -> 340.23452 | D40: =$B40*'1-基础参数'!$C$9*'1-基础参数'!$C$12*'1-基础参数'!$C$25*'1-基础参数'!$C$22+'2-单车成本测算'!$H$10*'1-基础参数'!$C$25*'1-基础参数'!$C$23 -> 407.85438 | E40: =(($B40*'1-基础参数'!$C$9*'1-基础参数'!$C$12-$B40*'1-基础参数'!$C$9*'1-基础参数'!$C$12*'1-基础参数'!$C$25*'1-基础参数'!$C$22)*(1-'1-基础参数'!$C$26)-'2-单车成本测算'!$G$21-'2-单车成本测算'!$G$28-'2-单车成本测算'!$G$24-'2-单车成本测算'!$G$32)*(1-'1-基础参数'!$C$33) -> 10010.316 | F40: =(($B40*'1-基础参数'!$C$9*'1-基础参数'!$C$12-$B40*'1-基础参数'!$C$9*'1-基础参数'!$C$12*'1-基础参数'!$C$25*'1-基础参数'!$C$22-'2-单车成本测算'!$H$10)*(1-'1-基础参数'!$C$26)-'2-单车成本测算'!$G$21-'2-单车成本测算'!$G$28-'2-单车成本测算'!$G$24-'2-单车成本测算'!$G$32)*(1-'1-基础参数'!$C$33) -> 3312.7222 | G40: =(($B40*'1-基础参数'!$C$9*'1-基础参数'!$C$12-$B40*'1-基础参数'!$C$9*'1-基础参数'!$C$12*'1-基础参数'!$C$25*'1-基础参数'!$C$22)*(1-'1-基础参数'!$C$26)-'2-单车成本测算'!$G$21-'2-单车成本测算'!$G$28-'2-单车成本测算'!$G$24-'2-单车成本测算'!$G$32)*'1-基础参数'!$C$33 -> 12234.831 | H40: =(($B40*'1-基础参数'!$C$9*'1-基础参数'!$C$12-$B40*'1-基础参数'!$C$9*'1-基础参数'!$C$12*'1-基础参数'!$C$25*'1-基础参数'!$C$22-'2-单车成本测算'!$H$10)*(1-'1-基础参数'!$C$26)-'2-单车成本测算'!$G$21-'2-单车成本测算'!$G$28-'2-单车成本测算'!$G$24-'2-单车成本测算'!$G$32)*'1-基础参数'!$C$33 -> 4048.8827 | I40: =C40+E40+G40+($B40*'1-基础参数'!$C$9*'1-基础参数'!$C$12-$B40*'1-基础参数'!$C$9*'1-基础参数'!$C$12*'1-基础参数'!$C$25*'1-基础参数'!$C$22)*'1-基础参数'!$C$26+('2-单车成本测算'!$G$21*'1-基础参数'!$C$27/'2-单车成本测算'!$E$15*'1-基础参数'!$C$28+'2-单车成本测算'!$G$28*'1-基础参数'!$C$29)*'1-基础参数'!$C$34+'2-单车成本测算'!$G$21*'1-基础参数'!$C$27/'2-单车成本测算'!$E$15*(1-'1-基础参数'!$C$28)+('2-单车成本测算'!$G$21*'1-基础参数'!$C$27/'2-单车成本测算'!$E$15*'1-基础参数'!$C$28+'2-单车成本测算'!$G$28*'1-基础参数'!$C$29)*(1-'1-基础参数'!$C$34) -> 31727.522 | J40: =D40+F40+H40+($B40*'1-基础参数'!$C$9*'1-基础参数'!$C$12-$B40*'1-基础参数'!$C$9*'1-基础参数'!$C$12*'1-基础参数'!$C$25*'1-基础参数'!$C$22-'2-单车成本测算'!$H$10)*'1-基础参数'!$C$26+200+('2-单车成本测算'!$G$21*'1-基础参数'!$C$27/'2-单车成本测算'!$E$15*'1-基础参数'!$C$28+'2-单车成本测算'!$G$28*'1-基础参数'!$C$29+'2-单车成本测算'!$G$14*'1-基础参数'!$C$30)*'1-基础参数'!$C$34+'2-单车成本测算'!$G$21*'1-基础参数'!$C$27/'2-单车成本测算'!$E$15*(1-'1-基础参数'!$C$28)+('2-单车成本测算'!$G$21*'1-基础参数'!$C$27/'2-单车成本测算'!$E$15*'1-基础参数'!$C$28+'2-单车成本测算'!$G$28*'1-基础参数'!$C$29+'2-单车成本测算'!$G$14*'1-基础参数'!$C$30)*(1-'1-基础参数'!$C$34)+'2-单车成本测算'!$G$9*0.15/1.15+'3.5-资金清分'!$E$55 -> 19498.199
B41: 231 | C41: =$B41*'1-基础参数'!$C$9*'1-基础参数'!$C$12*'1-基础参数'!$C$25*'1-基础参数'!$C$22 -> 374.25797 | D41: =$B41*'1-基础参数'!$C$9*'1-基础参数'!$C$12*'1-基础参数'!$C$25*'1-基础参数'!$C$22+'2-单车成本测算'!$H$10*'1-基础参数'!$C$25*'1-基础参数'!$C$23 -> 441.87784 | E41: =(($B41*'1-基础参数'!$C$9*'1-基础参数'!$C$12-$B41*'1-基础参数'!$C$9*'1-基础参数'!$C$12*'1-基础参数'!$C$25*'1-基础参数'!$C$22)*(1-'1-基础参数'!$C$26)-'2-单车成本测算'!$G$21-'2-单车成本测算'!$G$28-'2-单车成本测算'!$G$24-'2-单车成本测算'!$G$32)*(1-'1-基础参数'!$C$33) -> 13365.028 | F41: =(($B41*'1-基础参数'!$C$9*'1-基础参数'!$C$12-$B41*'1-基础参数'!$C$9*'1-基础参数'!$C$12*'1-基础参数'!$C$25*'1-基础参数'!$C$22-'2-单车成本测算'!$H$10)*(1-'1-基础参数'!$C$26)-'2-单车成本测算'!$G$21-'2-单车成本测算'!$G$28-'2-单车成本测算'!$G$24-'2-单车成本测算'!$G$32)*(1-'1-基础参数'!$C$33) -> 6667.4338 | G41: =(($B41*'1-基础参数'!$C$9*'1-基础参数'!$C$12-$B41*'1-基础参数'!$C$9*'1-基础参数'!$C$12*'1-基础参数'!$C$25*'1-基础参数'!$C$22)*(1-'1-基础参数'!$C$26)-'2-单车成本测算'!$G$21-'2-单车成本测算'!$G$28-'2-单车成本测算'!$G$24-'2-单车成本测算'!$G$32)*'1-基础参数'!$C$33 -> 16335.034 | H41: =(($B41*'1-基础参数'!$C$9*'1-基础参数'!$C$12-$B41*'1-基础参数'!$C$9*'1-基础参数'!$C$12*'1-基础参数'!$C$25*'1-基础参数'!$C$22-'2-单车成本测算'!$H$10)*(1-'1-基础参数'!$C$26)-'2-单车成本测算'!$G$21-'2-单车成本测算'!$G$28-'2-单车成本测算'!$G$24-'2-单车成本测算'!$G$32)*'1-基础参数'!$C$33 -> 8149.0858 | I41: =C41+E41+G41+($B41*'1-基础参数'!$C$9*'1-基础参数'!$C$12-$B41*'1-基础参数'!$C$9*'1-基础参数'!$C$12*'1-基础参数'!$C$25*'1-基础参数'!$C$22)*'1-基础参数'!$C$26+('2-单车成本测算'!$G$21*'1-基础参数'!$C$27/'2-单车成本测算'!$E$15*'1-基础参数'!$C$28+'2-单车成本测算'!$G$28*'1-基础参数'!$C$29)*'1-基础参数'!$C$34+'2-单车成本测算'!$G$21*'1-基础参数'!$C$27/'2-单车成本测算'!$E$15*(1-'1-基础参数'!$C$28)+('2-单车成本测算'!$G$21*'1-基础参数'!$C$27/'2-单车成本测算'!$E$15*'1-基础参数'!$C$28+'2-单车成本测算'!$G$28*'1-基础参数'!$C$29)*(1-'1-基础参数'!$C$34) -> 39253.922 | J41: =D41+F41+H41+($B41*'1-基础参数'!$C$9*'1-基础参数'!$C$12-$B41*'1-基础参数'!$C$9*'1-基础参数'!$C$12*'1-基础参数'!$C$25*'1-基础参数'!$C$22-'2-单车成本测算'!$H$10)*'1-基础参数'!$C$26+200+('2-单车成本测算'!$G$21*'1-基础参数'!$C$27/'2-单车成本测算'!$E$15*'1-基础参数'!$C$28+'2-单车成本测算'!$G$28*'1-基础参数'!$C$29+'2-单车成本测算'!$G$14*'1-基础参数'!$C$30)*'1-基础参数'!$C$34+'2-单车成本测算'!$G$21*'1-基础参数'!$C$27/'2-单车成本测算'!$E$15*(1-'1-基础参数'!$C$28)+('2-单车成本测算'!$G$21*'1-基础参数'!$C$27/'2-单车成本测算'!$E$15*'1-基础参数'!$C$28+'2-单车成本测算'!$G$28*'1-基础参数'!$C$29+'2-单车成本测算'!$G$14*'1-基础参数'!$C$30)*(1-'1-基础参数'!$C$34)+'2-单车成本测算'!$G$9*0.15/1.15+'3.5-资金清分'!$E$55 -> 27024.599
B42: 252 | C42: =$B42*'1-基础参数'!$C$9*'1-基础参数'!$C$12*'1-基础参数'!$C$25*'1-基础参数'!$C$22 -> 408.28142 | D42: =$B42*'1-基础参数'!$C$9*'1-基础参数'!$C$12*'1-基础参数'!$C$25*'1-基础参数'!$C$22+'2-单车成本测算'!$H$10*'1-基础参数'!$C$25*'1-基础参数'!$C$23 -> 475.90129 | E42: =(($B42*'1-基础参数'!$C$9*'1-基础参数'!$C$12-$B42*'1-基础参数'!$C$9*'1-基础参数'!$C$12*'1-基础参数'!$C$25*'1-基础参数'!$C$22)*(1-'1-基础参数'!$C$26)-'2-单车成本测算'!$G$21-'2-单车成本测算'!$G$28-'2-单车成本测算'!$G$24-'2-单车成本测算'!$G$32)*(1-'1-基础参数'!$C$33) -> 16719.739 | F42: =(($B42*'1-基础参数'!$C$9*'1-基础参数'!$C$12-$B42*'1-基础参数'!$C$9*'1-基础参数'!$C$12*'1-基础参数'!$C$25*'1-基础参数'!$C$22-'2-单车成本测算'!$H$10)*(1-'1-基础参数'!$C$26)-'2-单车成本测算'!$G$21-'2-单车成本测算'!$G$28-'2-单车成本测算'!$G$24-'2-单车成本测算'!$G$32)*(1-'1-基础参数'!$C$33) -> 10022.145 | G42: =(($B42*'1-基础参数'!$C$9*'1-基础参数'!$C$12-$B42*'1-基础参数'!$C$9*'1-基础参数'!$C$12*'1-基础参数'!$C$25*'1-基础参数'!$C$22)*(1-'1-基础参数'!$C$26)-'2-单车成本测算'!$G$21-'2-单车成本测算'!$G$28-'2-单车成本测算'!$G$24-'2-单车成本测算'!$G$32)*'1-基础参数'!$C$33 -> 20435.237 | H42: =(($B42*'1-基础参数'!$C$9*'1-基础参数'!$C$12-$B42*'1-基础参数'!$C$9*'1-基础参数'!$C$12*'1-基础参数'!$C$25*'1-基础参数'!$C$22-'2-单车成本测算'!$H$10)*(1-'1-基础参数'!$C$26)-'2-单车成本测算'!$G$21-'2-单车成本测算'!$G$28-'2-单车成本测算'!$G$24-'2-单车成本测算'!$G$32)*'1-基础参数'!$C$33 -> 12249.289 | I42: =C42+E42+G42+($B42*'1-基础参数'!$C$9*'1-基础参数'!$C$12-$B42*'1-基础参数'!$C$9*'1-基础参数'!$C$12*'1-基础参数'!$C$25*'1-基础参数'!$C$22)*'1-基础参数'!$C$26+('2-单车成本测算'!$G$21*'1-基础参数'!$C$27/'2-单车成本测算'!$E$15*'1-基础参数'!$C$28+'2-单车成本测算'!$G$28*'1-基础参数'!$C$29)*'1-基础参数'!$C$34+'2-单车成本测算'!$G$21*'1-基础参数'!$C$27/'2-单车成本测算'!$E$15*(1-'1-基础参数'!$C$28)+('2-单车成本测算'!$G$21*'1-基础参数'!$C$27/'2-单车成本测算'!$E$15*'1-基础参数'!$C$28+'2-单车成本测算'!$G$28*'1-基础参数'!$C$29)*(1-'1-基础参数'!$C$34) -> 46780.322 | J42: =D42+F42+H42+($B42*'1-基础参数'!$C$9*'1-基础参数'!$C$12-$B42*'1-基础参数'!$C$9*'1-基础参数'!$C$12*'1-基础参数'!$C$25*'1-基础参数'!$C$22-'2-单车成本测算'!$H$10)*'1-基础参数'!$C$26+200+('2-单车成本测算'!$G$21*'1-基础参数'!$C$27/'2-单车成本测算'!$E$15*'1-基础参数'!$C$28+'2-单车成本测算'!$G$28*'1-基础参数'!$C$29+'2-单车成本测算'!$G$14*'1-基础参数'!$C$30)*'1-基础参数'!$C$34+'2-单车成本测算'!$G$21*'1-基础参数'!$C$27/'2-单车成本测算'!$E$15*(1-'1-基础参数'!$C$28)+('2-单车成本测算'!$G$21*'1-基础参数'!$C$27/'2-单车成本测算'!$E$15*'1-基础参数'!$C$28+'2-单车成本测算'!$G$28*'1-基础参数'!$C$29+'2-单车成本测算'!$G$14*'1-基础参数'!$C$30)*(1-'1-基础参数'!$C$34)+'2-单车成本测算'!$G$9*0.15/1.15+'3.5-资金清分'!$E$55 -> 34550.999
B43: 273 | C43: =$B43*'1-基础参数'!$C$9*'1-基础参数'!$C$12*'1-基础参数'!$C$25*'1-基础参数'!$C$22 -> 442.30488 | D43: =$B43*'1-基础参数'!$C$9*'1-基础参数'!$C$12*'1-基础参数'!$C$25*'1-基础参数'!$C$22+'2-单车成本测算'!$H$10*'1-基础参数'!$C$25*'1-基础参数'!$C$23 -> 509.92474 | E43: =(($B43*'1-基础参数'!$C$9*'1-基础参数'!$C$12-$B43*'1-基础参数'!$C$9*'1-基础参数'!$C$12*'1-基础参数'!$C$25*'1-基础参数'!$C$22)*(1-'1-基础参数'!$C$26)-'2-单车成本测算'!$G$21-'2-单车成本测算'!$G$28-'2-单车成本测算'!$G$24-'2-单车成本测算'!$G$32)*(1-'1-基础参数'!$C$33) -> 20074.451 | F43: =(($B43*'1-基础参数'!$C$9*'1-基础参数'!$C$12-$B43*'1-基础参数'!$C$9*'1-基础参数'!$C$12*'1-基础参数'!$C$25*'1-基础参数'!$C$22-'2-单车成本测算'!$H$10)*(1-'1-基础参数'!$C$26)-'2-单车成本测算'!$G$21-'2-单车成本测算'!$G$28-'2-单车成本测算'!$G$24-'2-单车成本测算'!$G$32)*(1-'1-基础参数'!$C$33) -> 13376.857 | G43: =(($B43*'1-基础参数'!$C$9*'1-基础参数'!$C$12-$B43*'1-基础参数'!$C$9*'1-基础参数'!$C$12*'1-基础参数'!$C$25*'1-基础参数'!$C$22)*(1-'1-基础参数'!$C$26)-'2-单车成本测算'!$G$21-'2-单车成本测算'!$G$28-'2-单车成本测算'!$G$24-'2-单车成本测算'!$G$32)*'1-基础参数'!$C$33 -> 24535.44 | H43: =(($B43*'1-基础参数'!$C$9*'1-基础参数'!$C$12-$B43*'1-基础参数'!$C$9*'1-基础参数'!$C$12*'1-基础参数'!$C$25*'1-基础参数'!$C$22-'2-单车成本测算'!$H$10)*(1-'1-基础参数'!$C$26)-'2-单车成本测算'!$G$21-'2-单车成本测算'!$G$28-'2-单车成本测算'!$G$24-'2-单车成本测算'!$G$32)*'1-基础参数'!$C$33 -> 16349.492 | I43: =C43+E43+G43+($B43*'1-基础参数'!$C$9*'1-基础参数'!$C$12-$B43*'1-基础参数'!$C$9*'1-基础参数'!$C$12*'1-基础参数'!$C$25*'1-基础参数'!$C$22)*'1-基础参数'!$C$26+('2-单车成本测算'!$G$21*'1-基础参数'!$C$27/'2-单车成本测算'!$E$15*'1-基础参数'!$C$28+'2-单车成本测算'!$G$28*'1-基础参数'!$C$29)*'1-基础参数'!$C$34+'2-单车成本测算'!$G$21*'1-基础参数'!$C$27/'2-单车成本测算'!$E$15*(1-'1-基础参数'!$C$28)+('2-单车成本测算'!$G$21*'1-基础参数'!$C$27/'2-单车成本测算'!$E$15*'1-基础参数'!$C$28+'2-单车成本测算'!$G$28*'1-基础参数'!$C$29)*(1-'1-基础参数'!$C$34) -> 54306.722 | J43: =D43+F43+H43+($B43*'1-基础参数'!$C$9*'1-基础参数'!$C$12-$B43*'1-基础参数'!$C$9*'1-基础参数'!$C$12*'1-基础参数'!$C$25*'1-基础参数'!$C$22-'2-单车成本测算'!$H$10)*'1-基础参数'!$C$26+200+('2-单车成本测算'!$G$21*'1-基础参数'!$C$27/'2-单车成本测算'!$E$15*'1-基础参数'!$C$28+'2-单车成本测算'!$G$28*'1-基础参数'!$C$29+'2-单车成本测算'!$G$14*'1-基础参数'!$C$30)*'1-基础参数'!$C$34+'2-单车成本测算'!$G$21*'1-基础参数'!$C$27/'2-单车成本测算'!$E$15*(1-'1-基础参数'!$C$28)+('2-单车成本测算'!$G$21*'1-基础参数'!$C$27/'2-单车成本测算'!$E$15*'1-基础参数'!$C$28+'2-单车成本测算'!$G$28*'1-基础参数'!$C$29+'2-单车成本测算'!$G$14*'1-基础参数'!$C$30)*(1-'1-基础参数'!$C$34)+'2-单车成本测算'!$G$9*0.15/1.15+'3.5-资金清分'!$E$55 -> 42077.399

Sheet 持车公司财务分析
B2: 持车公司财务分析
B3: 本页按“持车服务公司+持车平台”合并口径测算，默认采用租赁模式全车队口径；收入取车赁全额，资本开支按车辆原值一次性投入，结果随基础参数自动联动。
B5: 关键假设 | F5: 关键结论
B6: 项目 | C6: 数值 | D6: 单位 | E6: 说明/来源 | F6: 指标 | G6: 结果 | H6: 单位 | I6: 说明
B7: 分析口径 | C7: ="持车服务公司+持车平台（合并）" -> 持车服务公司+持车平台（合并） | D7: 口径 | E7: 对应租赁模式持车主体 | F7: 总投资额 | G7: =($C$8*$C$9)/10000 -> 4600 | H7: 万元 | I7: 车辆数×单车购置成本
B8: 车辆数量 | C8: 100 | D8: 辆 | E8: 取租赁车辆数量 | F8: 初始投入 | G8: =(($C$8*$C$9)-($C$8*$C$10))/10000 -> 1090 | H8: 万元 | I8: 总投资-借款本金
B9: 单车购置成本 | C9: ='2-单车成本测算'!E5+'2-单车成本测算'!E6+'2-单车成本测算'!E7 -> 460000 | D9: 元/辆 | E9: 车头+挂车+补贴 | F9: 年均营业收入 | G9: =AVERAGE($C$21:$F$21)/10000 -> 1795 | H9: 万元 | I9: 利润表年均值
B10: 单车借款本金 | C10: ='2-单车成本测算'!E5*90% -> 351000 | D10: 元/辆 | E10: 按车头90%融资 | F10: 年均净利润 | G10: =AVERAGE($C$29:$F$29)/10000 -> 227.7086 | H10: 万元 | I10: 利润表年均值
B11: 融资年利率 | C11: ='1-基础参数'!C24 -> 0.055 | D11: % | E11: 引用基础参数 | F11: 4年累计净利润 | G11: =$G$29/10000 -> 910.83439 | H11: 万元 | I11: 利润表累计值
B12: 融资期限 | C12: =36 -> 36 | D12: 月 | E12: 与单车成本表金融利息口径一致 | F12: 总投资ROI | G12: =$G$29/($C$8*$C$9) -> 0.19800748 | H12: % | I12: 累计净利润/总投资
B13: 折旧年限 | C13: =4 -> 4 | D13: 年 | E13: 与当前模型4年摊销一致 | F13: 股权IRR | G13: =IRR($C$40:$G$40) -> 0.12597558 | H13: % | I13: 基于股权自由现金流
B14: 所得税率 | C14: =25% -> 0.25 | D14: % | E14: 可手动调整的假设 | F14: 现金回收倍数 | G14: =SUM($D$40:$G$40)/(-$C$40) -> 1.555303 | H14: x | I14: 累计回款/初始股权投入
B15: 单车月租金收入 | C15: ='3.5-资金清分'!E34/'1-基础参数'!C40 -> 14958.333 | D15: 元/辆/月 | E15: 含平台200元/台溢价 | F15: 静态回收期 | G15: =IF($D$41>=0,ABS($C$41)/$D$40,IF($E$41>=0,1+ABS($D$41)/$E$40,IF($F$41>=0,2+ABS($E$41)/$F$40,IF($G$41>=0,3+ABS($F$41)/$G$40,"未回收")))) -> 3.5782019 | H15: 年 | I15: 基于累计股权现金流
B16: 单车月保险成本 | C16: ='3.5-资金清分'!E54/'1-基础参数'!C40 -> 2208.3333 | D16: 元/辆/月 | E16: 引用持车服务公司保险支出
B17: 单车月债务本息 | C17: =-PMT($C$11/12,$C$12,$C$10) -> 10598.762 | D17: 元/辆/月 | E17: 本金+利息的月度合计
B19: 一、利润表（合并口径，元/年）
B20: 项目 | C20: Year1 | D20: Year2 | E20: Year3 | F20: Year4 | G20: 4年累计 | H20: 年均 | I20: 说明
B21: 营业收入 | C21: =($C$8*$C$15*12) -> 17950000 | D21: =($C$8*$C$15*12) -> 17950000 | E21: =($C$8*$C$15*12) -> 17950000 | F21: =($C$8*$C$15*12) -> 17950000 | G21: =SUM(C21:F21) -> 71800000 | H21: =AVERAGE(C21:F21) -> 17950000 | I21: 车赁收入（含平台溢价）
B22: 保险成本 | C22: =-( $C$8*$C$16*12 ) -> -2650000 | D22: =-( $C$8*$C$16*12 ) -> -2650000 | E22: =-( $C$8*$C$16*12 ) -> -2650000 | F22: =-( $C$8*$C$16*12 ) -> -2650000 | G22: =SUM(C22:F22) -> -10600000 | H22: =AVERAGE(C22:F22) -> -2650000 | I22: 持车服务公司承担的保险费
B23: EBITDA | C23: =SUM(C21:C22) -> 15300000 | D23: =SUM(D21:D22) -> 15300000 | E23: =SUM(E21:E22) -> 15300000 | F23: =SUM(F21:F22) -> 15300000 | G23: =SUM(C23:F23) -> 61200000 | H23: =AVERAGE(C23:F23) -> 15300000 | I23: 收入-经营成本
B24: 折旧 | C24: =-( $C$8*$C$9/$C$13 ) -> -11500000 | D24: =-( $C$8*$C$9/$C$13 ) -> -11500000 | E24: =-( $C$8*$C$9/$C$13 ) -> -11500000 | F24: =-( $C$8*$C$9/$C$13 ) -> -11500000 | G24: =SUM(C24:F24) -> -46000000 | H24: =AVERAGE(C24:F24) -> -11500000 | I24: 按4年直线法
B25: EBIT | C25: =SUM(C23:C24) -> 3800000 | D25: =SUM(D23:D24) -> 3800000 | E25: =SUM(E23:E24) -> 3800000 | F25: =SUM(F23:F24) -> 3800000 | G25: =SUM(C25:F25) -> 15200000 | H25: =AVERAGE(C25:F25) -> 3800000
B26: 利息费用 | C26: =CUMIPMT($C$11/12,$C$12,$C$10*$C$8,1,12,0) -> -1654354.2 | D26: =CUMIPMT($C$11/12,$C$12,$C$10*$C$8,13,24,0) -> -1030248.7 | E26: =CUMIPMT($C$11/12,$C$12,$C$10*$C$8,25,36,0) -> -370938.63 | F26: =0 -> 0 | G26: =SUM(C26:F26) -> -3055541.5 | H26: =AVERAGE(C26:F26) -> -763885.38 | I26: 按36个月贷款测算
B27: 税前利润 | C27: =SUM(C25:C26) -> 2145645.8 | D27: =SUM(D25:D26) -> 2769751.3 | E27: =SUM(E25:E26) -> 3429061.4 | F27: =SUM(F25:F26) -> 3800000 | G27: =SUM(C27:F27) -> 12144458 | H27: =AVERAGE(C27:F27) -> 3036114.6 | I27: EBIT-利息费用
B28: 所得税 | C28: =IF(C27>0,-C27*$C$14,0) -> -536411.44 | D28: =IF(D27>0,-D27*$C$14,0) -> -692437.84 | E28: =IF(E27>0,-E27*$C$14,0) -> -857265.34 | F28: =IF(F27>0,-F27*$C$14,0) -> -950000 | G28: =SUM(C28:F28) -> -3036114.6 | H28: =AVERAGE(C28:F28) -> -759028.66 | I28: 默认25%，可调整
B29: 净利润 | C29: =SUM(C27:C28) -> 1609234.3 | D29: =SUM(D27:D28) -> 2077313.5 | E29: =SUM(E27:E28) -> 2571796 | F29: =SUM(F27:F28) -> 2850000 | G29: =SUM(C29:F29) -> 9108343.9 | H29: =AVERAGE(C29:F29) -> 2277086 | I29: 税后利润
B31: 二、现金流量表（股权口径，元）
B32: 项目 | C32: Year0 | D32: Year1 | E32: Year2 | F32: Year3 | G32: Year4 | H32: 4年累计 | I32: 说明
B33: 净利润 | C33: =0 -> 0 | D33: =C29 -> 1609234.3 | E33: =D29 -> 2077313.5 | F33: =E29 -> 2571796 | G33: =F29 -> 2850000 | H33: =SUM(C33:G33) -> 9108343.9 | I33: 与利润表联动
B34: 加：折旧 | C34: =0 -> 0 | D34: =-C24 -> 11500000 | E34: =-D24 -> 11500000 | F34: =-E24 -> 11500000 | G34: =-F24 -> 11500000 | H34: =SUM(C34:G34) -> 46000000 | I34: 非现金费用加回
B35: 经营现金流 | C35: =SUM(C33:C34) -> 0 | D35: =SUM(D33:D34) -> 13109234 | E35: =SUM(E33:E34) -> 13577314 | F35: =SUM(F33:F34) -> 14071796 | G35: =SUM(G33:G34) -> 14350000 | H35: =SUM(C35:G35) -> 55108344 | I35: 净利润+折旧
B36: 资本开支 | C36: =-( $C$8*$C$9 ) -> -46000000 | D36: =0 -> 0 | E36: =0 -> 0 | F36: =0 -> 0 | G36: =0 -> 0 | H36: =SUM(C36:G36) -> -46000000 | I36: Year0一次性购置车辆
B37: 新增借款 | C37: =($C$8*$C$10) -> 35100000 | D37: =0 -> 0 | E37: =0 -> 0 | F37: =0 -> 0 | G37: =0 -> 0 | H37: =SUM(C37:G37) -> 35100000 | I37: 按车头90%融资
B38: 偿还本金 | C38: =0 -> 0 | D38: =CUMPRINC($C$11/12,$C$12,$C$10*$C$8,1,12,0) -> -11064160 | E38: =CUMPRINC($C$11/12,$C$12,$C$10*$C$8,13,24,0) -> -11688265 | F38: =CUMPRINC($C$11/12,$C$12,$C$10*$C$8,25,36,0) -> -12347575 | G38: =0 -> 0 | H38: =SUM(C38:G38) -> -35100000 | I38: 按等额本息分年还本
B39: 支付利息 | C39: =0 -> 0 | D39: =C26 -> -1654354.2 | E39: =D26 -> -1030248.7 | F39: =E26 -> -370938.63 | G39: =F26 -> 0 | H39: =SUM(C39:G39) -> -3055541.5 | I39: 与利润表利息一致
B40: 股权自由现金流 | C40: =SUM(C35:C39) -> -10900000 | D40: =SUM(D35:D39) -> 390720.49 | E40: =SUM(E35:E39) -> 858799.67 | F40: =SUM(F35:F39) -> 1353282.2 | G40: =SUM(G35:G39) -> 14350000 | H40: =SUM(C40:G40) -> 6052802.3 | I40: 经营现金流+投融资现金流
B41: 累计股权现金流 | C41: =C40 -> -10900000 | D41: =C41+D40 -> -10509280 | E41: =D41+E40 -> -9650479.8 | F41: =E41+F40 -> -8297197.7 | G41: =F41+G40 -> 6052802.3 | H41: =G41 -> 6052802.3 | I41: 用于测算回收期
B43: 三、投资收益ROI测算
B44: 指标 | C44: 结果 | D44: 单位 | E44: 口径说明
B45: 4年累计净利润 | C45: =$G$29/10000 -> 910.83439 | D45: 万元 | E45: 利润表净利润累计值
B46: 总投资额 | C46: =($C$8*$C$9)/10000 -> 4600 | D46: 万元 | E46: 车辆数×单车购置成本
B47: 总投资ROI | C47: =$G$29/($C$8*$C$9) -> 0.19800748 | D47: % | E47: 累计净利润/总投资
B48: 股权IRR | C48: =IRR($C$40:$G$40) -> 0.12597558 | D48: % | E48: 基于Year0~Year4股权自由现金流
B49: 现金回收倍数 | C49: =SUM($D$40:$G$40)/(-$C$40) -> 1.555303 | D49: x | E49: 累计回款/初始股权投入
B50: 静态回收期 | C50: =IF($D$41>=0,ABS($C$41)/$D$40,IF($E$41>=0,1+ABS($D$41)/$E$40,IF($F$41>=0,2+ABS($E$41)/$F$40,IF($G$41>=0,3+ABS($F$41)/$G$40,"未回收")))) -> 3.5782019 | D50: 年 | E50: 以累计现金流转正时点测算
B52: 测算口径说明： 1) 本页按“持车服务公司+持车平台”合并口径分析，避免内部车赁转付重复计算； 2) 收入采用车赁全额（含平台200元/台溢价），保险费按现有清分表引用； 3) 资本开支按车辆原值一次性投入，借款按车头90%、36个月、5.5%年利率测算； 4) 折旧采用4年直线法；所得税率默认25%，可在C14手动调整。

Sheet 7-双层熔断测算区
B2: 7-双层熔断测算区
B3: 按单车口径模拟合同物流企业熔断。单位统一为元/吨趟，判断逻辑为“扣减承运侧后是否还能覆盖合同物流企业刚性支出”。
B5: 项目 | C5: 默认引用值 | D5: 手工调整值 | E5: 采用值 | F5: 单位 | G5: 说明
B6: 货主支付物流费用 | C6: ='3-收益测算'!D6 -> 75264 | E6: =IF(D6="",C6,D6) -> 75264 | F6: 元/月 | G6: 单车月收入。
B7: 单车月运输吨数 | C7: ='1-基础参数'!C9*'1-基础参数'!C12 -> 358.4 | E7: =IF(D7="",C7,D7) -> 358.4 | F7: 吨/月 | G7: 载重×月趟数。
B8: 实际到手运价 | C8: =IFERROR(E6/E7,0) -> 210 | E8: =IF(D8="",C8,D8) -> 210 | F8: 元/吨趟 | G8: 用于与熔断线比较。
B10: 一、承运侧先扣项目
B11: 承运司机费用 | C11: ='3-收益测算'!D13 -> 20000 | E11: =IF(D11="",C11,D11) -> 20000 | F11: 元/月 | G11: 承运执行层人工。
B12: 承运管理费用 | C12: ='3-收益测算'!D15 -> 1000 | E12: =IF(D12="",C12,D12) -> 1000 | F12: 元/月 | G12: 承运执行层管理。
B13: 承运毛利 | C13: ='3.5-资金清分'!D46 -> 12234.831 | E13: =IF(D13="",C13,D13) -> 12234.831 | F13: 元/月 | G13: 承运物流企业执行层收益。
B14: 扣减承运侧后可用金额 | C14: =E6-E11-E12-E13 -> 42029.169 | E14: =IF(D14="",C14,D14) -> 42029.169 | F14: 元/月 | G14: 用于覆盖合同物流企业刚性支出。
B16: 二、合同物流企业刚性支出
B17: 垫资利息 | C17: ='3.5-资金清分'!D12 -> 340.23452 | E17: =IF(D17="",C17,D17) -> 340.23452 | F17: 元/月 | G17: 合同物流企业实际垫资收益/成本口径。
B18: 车辆租金（牵引车+挂车） | C18: ='2-单车成本测算'!H10 -> 14958.333 | E18: =IF(D18="",C18,D18) -> 14958.333 | F18: 元/月 | G18: 默认引用租赁口径，可按实际车租调整。
B19: 保险费用 | C19: ='3-收益测算'!D11 -> 2208.3333 | E19: =IF(D19="",C19,D19) -> 2208.3333 | F19: 元/月 | G19: 按单车月度保险口径。
B20: 能源费用 | C20: ='3-收益测算'!D12 -> 26936 | E20: =IF(D20="",C20,D20) -> 26936 | F20: 元/月 | G20: 合同物流企业实际承担的能源支出。
B21: 维保费用 | C21: ='3-收益测算'!D14 -> 4368 | E21: =IF(D21="",C21,D21) -> 4368 | F21: 元/月 | G21: 合同物流企业实际承担的维保支出。
B22: 合同物流企业刚性支出合计 | C22: =SUM(E17:E21) -> 48810.901 | E22: =IF(D22="",C22,D22) -> 48810.901 | F22: 元/月 | G22: 熔断判断的核心覆盖成本。
B23: 合同物流企业熔断线 | C23: =IFERROR(E22/E7,0) -> 136.19113 | E23: =IF(D23="",C23,D23) -> 136.19113 | F23: 元/吨趟 | G23: 刚性支出合计÷单车月运输吨数。
B25: 三、熔断判断
B26: 覆盖校验 | C26: =IF(E14>=E22,"通过","熔断报警") -> 熔断报警 | E26: =IF(D26="",C26,D26) -> 熔断报警 | F26: 文本 | G26: 扣减承运侧后可用金额是否足以覆盖刚性支出。
B27: 动作结论 | C27: =IF(E26="通过","继续执行","触发熔断预警，暂停新增并重谈价格") -> 触发熔断预警，暂停新增并重谈价格 | E27: =IF(D27="",C27,D27) -> 触发熔断预警，暂停新增并重谈价格 | F27: 文本 | G27: 合同物流企业不承担运价下行风险。
B28: 线序校验 | C28: =IF(E23<E8,"通过","口径待复核") -> 通过 | E28: =IF(D28="",C28,D28) -> 通过 | F28: 文本 | G28: 熔断线应低于当前实际到手运价。
B30: 说明 | C30: 当前副本先锁合同物流企业熔断逻辑。 | E30: 承运调节线后续再单独设计。 | F30: 文本 | G30: 避免把承运风险和合同物流企业刚性支出混算。
B31: 使用方式 | C31: 优先改D列 | E31: 按月输入实际承运毛利、车租、能源、维保、保险及结算金额。 | F31: 文本 | G31: 适合先做单车熔断模拟，再扩展到全项目。
